[{"id": "machine_0001", "img": "q/machine/0001.webp", "ans": 2, "page": 38, "q": 2, "diff": 0, "src": ""}, {"id": "machine_0002", "img": "q/machine/0002.webp", "ans": 2, "page": 38, "q": 4, "diff": 1, "src": "93.기사, 76.산업기사"}, {"id": "machine_0003", "img": "q/machine/0003.webp", "ans": 3, "page": 39, "q": 5, "diff": 0, "src": ""}, {"id": "machine_0004", "img": "q/machine/0004.webp", "ans": 2, "page": 39, "q": 6, "diff": 1, "src": "82. 기사"}, {"id": "machine_0005", "img": "q/machine/0005.webp", "ans": 4, "page": 39, "q": 7, "diff": 1, "src": "82. 83.98. 산업기사"}, {"id": "machine_0006", "img": "q/machine/0006.webp", "ans": 4, "page": 39, "q": 8, "diff": 0, "src": "00. 산업기사"}, {"id": "machine_0007", "img": "q/machine/0007.webp", "ans": 4, "page": 40, "q": 9, "diff": 0, "src": ""}, {"id": "machine_0008", "img": "q/machine/0008.webp", "ans": 2, "page": 40, "q": 10, "diff": 0, "src": ""}, {"id": "machine_0009", "img": "q/machine/0009.webp", "ans": 4, "page": 40, "q": 12, "diff": 5, "src": ""}, {"id": "machine_0010", "img": "q/machine/0010.webp", "ans": 4, "page": 41, "q": 13, "diff": 1, "src": ""}, {"id": "machine_0011", "img": "q/machine/0011.webp", "ans": 4, "page": 41, "q": 14, "diff": 4, "src": "89. 91. 98. 99. 기사, 77. 89. 92. 산업기사"}, {"id": "machine_0012", "img": "q/machine/0012.webp", "ans": 4, "page": 41, "q": 15, "diff": 1, "src": "95.11. 기사"}, {"id": "machine_0013", "img": "q/machine/0013.webp", "ans": 1, "page": 42, "q": 16, "diff": 2, "src": "05. 기사, 92. 99.02. 산업기사"}, {"id": "machine_0014", "img": "q/machine/0014.webp", "ans": 2, "page": 42, "q": 17, "diff": 4, "src": "85. 89. 94. 97.11. 기사, 83. 산업기사"}, {"id": "machine_0015", "img": "q/machine/0015.webp", "ans": 1, "page": 42, "q": 18, "diff": 0, "src": "94. 기사"}, {"id": "machine_0016", "img": "q/machine/0016.webp", "ans": 1, "page": 42, "q": 19, "diff": 0, "src": ""}, {"id": "machine_0017", "img": "q/machine/0017.webp", "ans": 3, "page": 42, "q": 20, "diff": 5, "src": "82. 83. 84. 88. 94. 98. 00. 기사, 85.11. 산업기사, ® : 85. 93. 기사, 87. 91. 97. 산업기사"}, {"id": "machine_0018", "img": "q/machine/0018.webp", "ans": 2, "page": 43, "q": 21, "diff": 0, "src": ""}, {"id": "machine_0019", "img": "q/machine/0019.webp", "ans": 4, "page": 43, "q": 22, "diff": 1, "src": "03. 기사"}, {"id": "machine_0020", "img": "q/machine/0020.webp", "ans": 4, "page": 43, "q": 23, "diff": 1, "src": ""}, {"id": "machine_0021", "img": "q/machine/0021.webp", "ans": 2, "page": 44, "q": 24, "diff": 1, "src": "89. 기사, 80. 20. 산업기사"}, {"id": "machine_0022", "img": "q/machine/0022.webp", "ans": 2, "page": 44, "q": 25, "diff": 1, "src": ""}, {"id": "machine_0023", "img": "q/machine/0023.webp", "ans": 4, "page": 45, "q": 26, "diff": 2, "src": "96. 기사, 91. 01.11. 산업기사"}, {"id": "machine_0024", "img": "q/machine/0024.webp", "ans": 2, "page": 45, "q": 27, "diff": 0, "src": "83.산업기사"}, {"id": "machine_0025", "img": "q/machine/0025.webp", "ans": 4, "page": 45, "q": 29, "diff": 0, "src": ""}, {"id": "machine_0026", "img": "q/machine/0026.webp", "ans": 3, "page": 46, "q": 30, "diff": 2, "src": "80. 83. 93. 산업기사, ® : 82. 산업기사"}, {"id": "machine_0027", "img": "q/machine/0027.webp", "ans": 1, "page": 46, "q": 31, "diff": 5, "src": ""}, {"id": "machine_0028", "img": "q/machine/0028.webp", "ans": 4, "page": 46, "q": 32, "diff": 3, "src": "79. 83. 93. 기사"}, {"id": "machine_0029", "img": "q/machine/0029.webp", "ans": 4, "page": 47, "q": 33, "diff": 0, "src": ""}, {"id": "machine_0030", "img": "q/machine/0030.webp", "ans": 3, "page": 47, "q": 34, "diff": 5, "src": "83. 87. 88. 94. 97. 기사, 68. 산업기사"}, {"id": "machine_0031", "img": "q/machine/0031.webp", "ans": 3, "page": 47, "q": 35, "diff": 0, "src": "91. 96. 97. 기사, 80. 86. 95. 04. 06. 08.10.11.12. 20. 산업기사"}, {"id": "machine_0032", "img": "q/machine/0032.webp", "ans": 1, "page": 47, "q": 36, "diff": 1, "src": "03.12. 기사"}, {"id": "machine_0033", "img": "q/machine/0033.webp", "ans": 2, "page": 48, "q": 37, "diff": 3, "src": "92. 97. 00. 기사, ® ： 11. 기사, 93. 산업기사"}, {"id": "machine_0034", "img": "q/machine/0034.webp", "ans": 2, "page": 48, "q": 38, "diff": 2, "src": "82. 98. 01. 20. 산업기사"}, {"id": "machine_0035", "img": "q/machine/0035.webp", "ans": 2, "page": 48, "q": 39, "diff": 0, "src": ""}, {"id": "machine_0036", "img": "q/machine/0036.webp", "ans": 1, "page": 48, "q": 40, "diff": 3, "src": "82. 83. 기사, 80. 산업기사, 유 ： 92. 산업기사"}, {"id": "machine_0037", "img": "q/machine/0037.webp", "ans": 2, "page": 51, "q": 46, "diff": 1, "src": "03. 기사, 89. 98. 산업기사"}, {"id": "machine_0038", "img": "q/machine/0038.webp", "ans": 2, "page": 51, "q": 47, "diff": 3, "src": ""}, {"id": "machine_0039", "img": "q/machine/0039.webp", "ans": 3, "page": 51, "q": 48, "diff": 0, "src": ""}, {"id": "machine_0040", "img": "q/machine/0040.webp", "ans": 3, "page": 51, "q": 49, "diff": 1, "src": ""}, {"id": "machine_0041", "img": "q/machine/0041.webp", "ans": 3, "page": 51, "q": 50, "diff": 0, "src": ""}, {"id": "machine_0042", "img": "q/machine/0042.webp", "ans": 2, "page": 52, "q": 51, "diff": 0, "src": ""}, {"id": "machine_0043", "img": "q/machine/0043.webp", "ans": 1, "page": 52, "q": 53, "diff": 1, "src": "03. 기사"}, {"id": "machine_0044", "img": "q/machine/0044.webp", "ans": 4, "page": 52, "q": 54, "diff": 0, "src": ""}, {"id": "machine_0045", "img": "q/machine/0045.webp", "ans": 3, "page": 52, "q": 55, "diff": 5, "src": ""}, {"id": "machine_0046", "img": "q/machine/0046.webp", "ans": 3, "page": 53, "q": 56, "diff": 1, "src": "82. 85. 96. 99. 05. 25. 산업기사"}, {"id": "machine_0047", "img": "q/machine/0047.webp", "ans": 2, "page": 53, "q": 57, "diff": 0, "src": ""}, {"id": "machine_0048", "img": "q/machine/0048.webp", "ans": 4, "page": 53, "q": 58, "diff": 1, "src": "97. 20. 기사"}, {"id": "machine_0049", "img": "q/machine/0049.webp", "ans": 3, "page": 54, "q": 60, "diff": 0, "src": "83.산업기사"}, {"id": "machine_0050", "img": "q/machine/0050.webp", "ans": 4, "page": 54, "q": 61, "diff": 0, "src": ""}, {"id": "machine_0051", "img": "q/machine/0051.webp", "ans": 3, "page": 54, "q": 62, "diff": 0, "src": "95.03. 산업기사"}, {"id": "machine_0052", "img": "q/machine/0052.webp", "ans": 4, "page": 55, "q": 63, "diff": 0, "src": "80. 산업기사"}, {"id": "machine_0053", "img": "q/machine/0053.webp", "ans": 4, "page": 55, "q": 64, "diff": 1, "src": "80.98. 산업기사"}, {"id": "machine_0054", "img": "q/machine/0054.webp", "ans": 2, "page": 55, "q": 65, "diff": 2, "src": "85. 92.12. 기사"}, {"id": "machine_0055", "img": "q/machine/0055.webp", "ans": 3, "page": 55, "q": 66, "diff": 0, "src": ""}, {"id": "machine_0056", "img": "q/machine/0056.webp", "ans": 3, "page": 56, "q": 67, "diff": 1, "src": "93. 기사"}, {"id": "machine_0057", "img": "q/machine/0057.webp", "ans": 3, "page": 56, "q": 68, "diff": 1, "src": "79.83. 92.09. 산업기사"}, {"id": "machine_0058", "img": "q/machine/0058.webp", "ans": 2, "page": 56, "q": 69, "diff": 0, "src": ""}, {"id": "machine_0059", "img": "q/machine/0059.webp", "ans": 3, "page": 57, "q": 70, "diff": 4, "src": ""}, {"id": "machine_0060", "img": "q/machine/0060.webp", "ans": 3, "page": 57, "q": 71, "diff": 5, "src": ""}, {"id": "machine_0061", "img": "q/machine/0061.webp", "ans": 2, "page": 57, "q": 72, "diff": 0, "src": ""}, {"id": "machine_0062", "img": "q/machine/0062.webp", "ans": 2, "page": 58, "q": 73, "diff": 0, "src": "78. 98. 산업기사, ® : 97. 산업기사"}, {"id": "machine_0063", "img": "q/machine/0063.webp", "ans": 1, "page": 58, "q": 74, "diff": 0, "src": "01.산업기사"}, {"id": "machine_0064", "img": "q/machine/0064.webp", "ans": 2, "page": 58, "q": 75, "diff": 2, "src": "94.10.11. 기사, ⑧ : 92. 기사, 16. 산업기사"}, {"id": "machine_0065", "img": "q/machine/0065.webp", "ans": 2, "page": 58, "q": 76, "diff": 2, "src": "92. 기사, ® : 77. 기사"}, {"id": "machine_0066", "img": "q/machine/0066.webp", "ans": 3, "page": 60, "q": 79, "diff": 0, "src": "95. 03. 산업기사"}, {"id": "machine_0067", "img": "q/machine/0067.webp", "ans": 3, "page": 60, "q": 80, "diff": 0, "src": "94.산업기사"}, {"id": "machine_0068", "img": "q/machine/0068.webp", "ans": 2, "page": 62, "q": 81, "diff": 0, "src": ""}, {"id": "machine_0069", "img": "q/machine/0069.webp", "ans": 2, "page": 62, "q": 82, "diff": 1, "src": "77. 98. 25. 산업기사"}, {"id": "machine_0070", "img": "q/machine/0070.webp", "ans": 2, "page": 63, "q": 84, "diff": 2, "src": "78. 93. 97. 01. 03. 산업기사"}, {"id": "machine_0071", "img": "q/machine/0071.webp", "ans": 4, "page": 63, "q": 85, "diff": 0, "src": ""}, {"id": "machine_0072", "img": "q/machine/0072.webp", "ans": 4, "page": 64, "q": 86, "diff": 2, "src": "91. 기사, 91. 99. 산업기사"}, {"id": "machine_0073", "img": "q/machine/0073.webp", "ans": 1, "page": 64, "q": 87, "diff": 0, "src": ""}, {"id": "machine_0074", "img": "q/machine/0074.webp", "ans": 2, "page": 64, "q": 88, "diff": 4, "src": ""}, {"id": "machine_0075", "img": "q/machine/0075.webp", "ans": 1, "page": 64, "q": 89, "diff": 0, "src": ""}, {"id": "machine_0076", "img": "q/machine/0076.webp", "ans": 4, "page": 65, "q": 91, "diff": 0, "src": ""}, {"id": "machine_0077", "img": "q/machine/0077.webp", "ans": 3, "page": 65, "q": 92, "diff": 1, "src": ""}, {"id": "machine_0078", "img": "q/machine/0078.webp", "ans": 2, "page": 65, "q": 93, "diff": 0, "src": ""}, {"id": "machine_0079", "img": "q/machine/0079.webp", "ans": 3, "page": 65, "q": 94, "diff": 2, "src": "99.00. 기사"}, {"id": "machine_0080", "img": "q/machine/0080.webp", "ans": 4, "page": 66, "q": 95, "diff": 2, "src": "84. 93. 기사"}, {"id": "machine_0081", "img": "q/machine/0081.webp", "ans": 2, "page": 67, "q": 96, "diff": 1, "src": "93. 기사, ⑶ : 95. 산업기사"}, {"id": "machine_0082", "img": "q/machine/0082.webp", "ans": 2, "page": 67, "q": 97, "diff": 0, "src": ""}, {"id": "machine_0083", "img": "q/machine/0083.webp", "ans": 2, "page": 68, "q": 98, "diff": 3, "src": "93. 기사, 69. 산업기사, ® : 89. 95. 기사"}, {"id": "machine_0084", "img": "q/machine/0084.webp", "ans": 1, "page": 68, "q": 101, "diff": 0, "src": ""}, {"id": "machine_0085", "img": "q/machine/0085.webp", "ans": 3, "page": 68, "q": 102, "diff": 0, "src": "93. 산업기사"}, {"id": "machine_0086", "img": "q/machine/0086.webp", "ans": 4, "page": 69, "q": 103, "diff": 1, "src": "69.산업기사, 82. 94. 기사, ®: 79. 기사"}, {"id": "machine_0087", "img": "q/machine/0087.webp", "ans": 2, "page": 69, "q": 104, "diff": 1, "src": "96. 00. 01. 산업기사"}, {"id": "machine_0088", "img": "q/machine/0088.webp", "ans": 4, "page": 69, "q": 105, "diff": 0, "src": ""}, {"id": "machine_0089", "img": "q/machine/0089.webp", "ans": 3, "page": 69, "q": 106, "diff": 2, "src": "99.00. 기사"}, {"id": "machine_0090", "img": "q/machine/0090.webp", "ans": 2, "page": 69, "q": 107, "diff": 2, "src": "93. 기사, ® ： 92. 기사"}, {"id": "machine_0091", "img": "q/machine/0091.webp", "ans": 1, "page": 70, "q": 109, "diff": 4, "src": "98. 00. 05. 기사, 87. 91. 94. 95. 02.11. 산업기사"}, {"id": "machine_0092", "img": "q/machine/0092.webp", "ans": 2, "page": 70, "q": 110, "diff": 0, "src": "88.01. 기사"}, {"id": "machine_0093", "img": "q/machine/0093.webp", "ans": 4, "page": 70, "q": 111, "diff": 0, "src": ""}, {"id": "machine_0094", "img": "q/machine/0094.webp", "ans": 3, "page": 71, "q": 113, "diff": 2, "src": "81. 82. 90. 98. 산업기사"}, {"id": "machine_0095", "img": "q/machine/0095.webp", "ans": 2, "page": 71, "q": 115, "diff": 0, "src": ""}, {"id": "machine_0096", "img": "q/machine/0096.webp", "ans": 4, "page": 72, "q": 116, "diff": 3, "src": "79. 94. 기사，68. 80. 산업기사"}, {"id": "machine_0097", "img": "q/machine/0097.webp", "ans": 2, "page": 72, "q": 117, "diff": 4, "src": "77. 88. 89. 92. 95. 98. 00. 03. 05.11. 산업기사"}, {"id": "machine_0098", "img": "q/machine/0098.webp", "ans": 2, "page": 73, "q": 118, "diff": 4, "src": "94. 기사, ® : 78. 90. 92. 기사, 93. 94. 97. 산업기사"}, {"id": "machine_0099", "img": "q/machine/0099.webp", "ans": 4, "page": 73, "q": 119, "diff": 2, "src": "93.01. 기사"}, {"id": "machine_0100", "img": "q/machine/0100.webp", "ans": 1, "page": 74, "q": 120, "diff": 1, "src": "98. 기사"}, {"id": "machine_0101", "img": "q/machine/0101.webp", "ans": 2, "page": 74, "q": 121, "diff": 0, "src": ""}, {"id": "machine_0102", "img": "q/machine/0102.webp", "ans": 1, "page": 74, "q": 122, "diff": 0, "src": "97. 산업기사"}, {"id": "machine_0103", "img": "q/machine/0103.webp", "ans": 1, "page": 75, "q": 123, "diff": 4, "src": "90. 98. 99. 00. 기사"}, {"id": "machine_0104", "img": "q/machine/0104.webp", "ans": 3, "page": 75, "q": 124, "diff": 3, "src": ""}, {"id": "machine_0105", "img": "q/machine/0105.webp", "ans": 4, "page": 75, "q": 125, "diff": 2, "src": "89. 01. 기사"}, {"id": "machine_0106", "img": "q/machine/0106.webp", "ans": 3, "page": 75, "q": 126, "diff": 2, "src": "82. 85. 92. 97. 산업기사"}, {"id": "machine_0107", "img": "q/machine/0107.webp", "ans": 3, "page": 76, "q": 127, "diff": 3, "src": ""}, {"id": "machine_0108", "img": "q/machine/0108.webp", "ans": 2, "page": 76, "q": 128, "diff": 3, "src": ""}, {"id": "machine_0109", "img": "q/machine/0109.webp", "ans": 1, "page": 76, "q": 129, "diff": 0, "src": "93.산업기사"}, {"id": "machine_0110", "img": "q/machine/0110.webp", "ans": 1, "page": 77, "q": 131, "diff": 0, "src": ""}, {"id": "machine_0111", "img": "q/machine/0111.webp", "ans": 3, "page": 78, "q": 132, "diff": 2, "src": "97. 98. 기사"}, {"id": "machine_0112", "img": "q/machine/0112.webp", "ans": 1, "page": 79, "q": 133, "diff": 0, "src": ""}, {"id": "machine_0113", "img": "q/machine/0113.webp", "ans": 2, "page": 79, "q": 134, "diff": 3, "src": ""}, {"id": "machine_0114", "img": "q/machine/0114.webp", "ans": 3, "page": 79, "q": 135, "diff": 1, "src": "85. 01. 기사, ® ： 90. 산업기사"}, {"id": "machine_0115", "img": "q/machine/0115.webp", "ans": 2, "page": 79, "q": 136, "diff": 1, "src": "11. 기사,01. 산업기사"}, {"id": "machine_0116", "img": "q/machine/0116.webp", "ans": 3, "page": 79, "q": 137, "diff": 1, "src": "77. 78. 88. 94. 95. 98. 00.03.14. 산업기사, ®: 83. 90. 91. 산업기사"}, {"id": "machine_0117", "img": "q/machine/0117.webp", "ans": 1, "page": 80, "q": 138, "diff": 4, "src": "92. 기사, ® : 82. 83. 88. 89. 92. 98. 산업기사"}, {"id": "machine_0118", "img": "q/machine/0118.webp", "ans": 2, "page": 80, "q": 139, "diff": 3, "src": "82. 83. 85. 89. 95. 99. 09. 산업기사® 05. 기사"}, {"id": "machine_0119", "img": "q/machine/0119.webp", "ans": 4, "page": 80, "q": 140, "diff": 3, "src": ""}, {"id": "machine_0120", "img": "q/machine/0120.webp", "ans": 3, "page": 80, "q": 141, "diff": 1, "src": "92. 기사"}, {"id": "machine_0121", "img": "q/machine/0121.webp", "ans": 4, "page": 81, "q": 143, "diff": 5, "src": "89.11. 05. 기사, 88. 98. 00. 03. 07. 산업기사, ® : 70. 80. 85. 89. 91. 96. 기사"}, {"id": "machine_0122", "img": "q/machine/0122.webp", "ans": 2, "page": 81, "q": 145, "diff": 2, "src": "92. 01. 기사"}, {"id": "machine_0123", "img": "q/machine/0123.webp", "ans": 4, "page": 81, "q": 146, "diff": 2, "src": "92. 96.12. 16.18. 산업기사, 證 : 78. 96. 산업기사"}, {"id": "machine_0124", "img": "q/machine/0124.webp", "ans": 1, "page": 82, "q": 147, "diff": 0, "src": "91.산업기사"}, {"id": "machine_0125", "img": "q/machine/0125.webp", "ans": 2, "page": 85, "q": 152, "diff": 0, "src": "78. 99. 03. 05. 산업기사"}, {"id": "machine_0126", "img": "q/machine/0126.webp", "ans": 4, "page": 86, "q": 153, "diff": 3, "src": ""}, {"id": "machine_0127", "img": "q/machine/0127.webp", "ans": 4, "page": 86, "q": 156, "diff": 5, "src": "83. 89. 96. 기사, 80. 81. 82. 85. 92. 05.18. 산업기사"}, {"id": "machine_0128", "img": "q/machine/0128.webp", "ans": 3, "page": 87, "q": 158, "diff": 0, "src": "91.산업기사"}, {"id": "machine_0129", "img": "q/machine/0129.webp", "ans": 3, "page": 87, "q": 159, "diff": 1, "src": "88. 98. 기사, 76. 90. 99. 산업기사"}, {"id": "machine_0130", "img": "q/machine/0130.webp", "ans": 3, "page": 88, "q": 160, "diff": 1, "src": "03. 기사, 82. 88. 95. 05. 산업기사"}, {"id": "machine_0131", "img": "q/machine/0131.webp", "ans": 3, "page": 88, "q": 161, "diff": 5, "src": "84. 89. 94. 03. 기사, 76. 80. 83. 88. 90. 산업기사"}, {"id": "machine_0132", "img": "q/machine/0132.webp", "ans": 4, "page": 88, "q": 162, "diff": 5, "src": "90. 95. 기사, 79. 88. 산업기사, ③ : 85. 97. 기사, 83. 05. 산업기사"}, {"id": "machine_0133", "img": "q/machine/0133.webp", "ans": 4, "page": 88, "q": 163, "diff": 3, "src": "77. 85. 92.10.18. 기사"}, {"id": "machine_0134", "img": "q/machine/0134.webp", "ans": 4, "page": 89, "q": 166, "diff": 0, "src": ""}, {"id": "machine_0135", "img": "q/machine/0135.webp", "ans": 2, "page": 90, "q": 168, "diff": 2, "src": "91.99. 기사"}, {"id": "machine_0136", "img": "q/machine/0136.webp", "ans": 2, "page": 90, "q": 169, "diff": 1, "src": "99. 기사"}, {"id": "machine_0137", "img": "q/machine/0137.webp", "ans": 1, "page": 91, "q": 170, "diff": 2, "src": "86.96. 기사"}, {"id": "machine_0138", "img": "q/machine/0138.webp", "ans": 1, "page": 91, "q": 171, "diff": 0, "src": ""}, {"id": "machine_0139", "img": "q/machine/0139.webp", "ans": 1, "page": 91, "q": 172, "diff": 1, "src": ""}, {"id": "machine_0140", "img": "q/machine/0140.webp", "ans": 3, "page": 92, "q": 176, "diff": 0, "src": ""}, {"id": "machine_0141", "img": "q/machine/0141.webp", "ans": 1, "page": 93, "q": 177, "diff": 0, "src": ""}, {"id": "machine_0142", "img": "q/machine/0142.webp", "ans": 2, "page": 93, "q": 178, "diff": 1, "src": ""}, {"id": "machine_0143", "img": "q/machine/0143.webp", "ans": 3, "page": 93, "q": 179, "diff": 2, "src": "91. 99. 기사"}, {"id": "machine_0144", "img": "q/machine/0144.webp", "ans": 1, "page": 93, "q": 180, "diff": 1, "src": "82. 83.16. 산업기사"}, {"id": "machine_0145", "img": "q/machine/0145.webp", "ans": 4, "page": 94, "q": 181, "diff": 0, "src": ""}, {"id": "machine_0146", "img": "q/machine/0146.webp", "ans": 3, "page": 94, "q": 182, "diff": 0, "src": "94.산업기사"}, {"id": "machine_0147", "img": "q/machine/0147.webp", "ans": 1, "page": 95, "q": 184, "diff": 1, "src": "99. 00. 기사"}, {"id": "machine_0148", "img": "q/machine/0148.webp", "ans": 2, "page": 115, "q": 2, "diff": 1, "src": "87. 기사"}, {"id": "machine_0149", "img": "q/machine/0149.webp", "ans": 2, "page": 115, "q": 3, "diff": 1, "src": "02. 25. 기사"}, {"id": "machine_0150", "img": "q/machine/0150.webp", "ans": 2, "page": 115, "q": 4, "diff": 4, "src": "85. 92. 00. 20. 기사, ® : 94. 기사"}, {"id": "machine_0151", "img": "q/machine/0151.webp", "ans": 2, "page": 116, "q": 5, "diff": 1, "src": "92. 기사"}, {"id": "machine_0152", "img": "q/machine/0152.webp", "ans": 3, "page": 116, "q": 7, "diff": 2, "src": "89. 97. 기사"}, {"id": "machine_0153", "img": "q/machine/0153.webp", "ans": 4, "page": 116, "q": 8, "diff": 5, "src": ""}, {"id": "machine_0154", "img": "q/machine/0154.webp", "ans": 3, "page": 117, "q": 9, "diff": 2, "src": "82.85. 93. 00. 산업기사"}, {"id": "machine_0155", "img": "q/machine/0155.webp", "ans": 2, "page": 117, "q": 10, "diff": 1, "src": ""}, {"id": "machine_0156", "img": "q/machine/0156.webp", "ans": 4, "page": 118, "q": 11, "diff": 0, "src": ""}, {"id": "machine_0157", "img": "q/machine/0157.webp", "ans": 4, "page": 118, "q": 12, "diff": 3, "src": "82. 94. 98.25. 기사"}, {"id": "machine_0158", "img": "q/machine/0158.webp", "ans": 1, "page": 118, "q": 13, "diff": 1, "src": "67. 기사, 84. 91. 00. 03. 산업기사"}, {"id": "machine_0159", "img": "q/machine/0159.webp", "ans": 3, "page": 118, "q": 14, "diff": 3, "src": "79. 기사, 69. 84. 93. 99. 산업기사"}, {"id": "machine_0160", "img": "q/machine/0160.webp", "ans": 4, "page": 118, "q": 15, "diff": 1, "src": "81. 82. 88. 94. 08. 12. 산업기사"}, {"id": "machine_0161", "img": "q/machine/0161.webp", "ans": 1, "page": 119, "q": 16, "diff": 1, "src": "89. 96. 산업기사"}, {"id": "machine_0162", "img": "q/machine/0162.webp", "ans": 2, "page": 119, "q": 17, "diff": 2, "src": "91.00. 기사"}, {"id": "machine_0163", "img": "q/machine/0163.webp", "ans": 3, "page": 119, "q": 18, "diff": 1, "src": "82. 83. 88. 산업기사"}, {"id": "machine_0164", "img": "q/machine/0164.webp", "ans": 3, "page": 119, "q": 19, "diff": 0, "src": ""}, {"id": "machine_0165", "img": "q/machine/0165.webp", "ans": 3, "page": 120, "q": 20, "diff": 5, "src": ""}, {"id": "machine_0166", "img": "q/machine/0166.webp", "ans": 1, "page": 120, "q": 21, "diff": 0, "src": ""}, {"id": "machine_0167", "img": "q/machine/0167.webp", "ans": 2, "page": 121, "q": 23, "diff": 0, "src": ""}, {"id": "machine_0168", "img": "q/machine/0168.webp", "ans": 2, "page": 121, "q": 24, "diff": 3, "src": "88.93.00.08.11.기사"}, {"id": "machine_0169", "img": "q/machine/0169.webp", "ans": 1, "page": 121, "q": 25, "diff": 1, "src": "01.11. 기사"}, {"id": "machine_0170", "img": "q/machine/0170.webp", "ans": 1, "page": 121, "q": 26, "diff": 5, "src": ""}, {"id": "machine_0171", "img": "q/machine/0171.webp", "ans": 4, "page": 122, "q": 27, "diff": 0, "src": ""}, {"id": "machine_0172", "img": "q/machine/0172.webp", "ans": 4, "page": 122, "q": 28, "diff": 1, "src": "03. 기사，91. 98. 00. 산업기사"}, {"id": "machine_0173", "img": "q/machine/0173.webp", "ans": 3, "page": 122, "q": 29, "diff": 1, "src": "01.25.기사"}, {"id": "machine_0174", "img": "q/machine/0174.webp", "ans": 4, "page": 122, "q": 30, "diff": 3, "src": "82. 83. 91. 기사"}, {"id": "machine_0175", "img": "q/machine/0175.webp", "ans": 3, "page": 123, "q": 31, "diff": 5, "src": "78. 79. 93. 94. 98. 99. 01. 05. 08. 09. 기사, 83. 88. 94. 00. 01. 03.11. 산업기사"}, {"id": "machine_0176", "img": "q/machine/0176.webp", "ans": 1, "page": 123, "q": 32, "diff": 3, "src": "98. 99. 00. 기사"}, {"id": "machine_0177", "img": "q/machine/0177.webp", "ans": 4, "page": 123, "q": 33, "diff": 1, "src": "92.99. 기사, 93. 산업기사"}, {"id": "machine_0178", "img": "q/machine/0178.webp", "ans": 3, "page": 123, "q": 34, "diff": 1, "src": "97. 기사"}, {"id": "machine_0179", "img": "q/machine/0179.webp", "ans": 1, "page": 123, "q": 35, "diff": 5, "src": "77. 99 16. 기사, 80. 81. 82. 84. 85. 86. 92. 93. 산업기사"}, {"id": "machine_0180", "img": "q/machine/0180.webp", "ans": 1, "page": 124, "q": 36, "diff": 2, "src": "92.10. 기사, 81. 82. 86. 89. 98. 02. 04. 08.12. 20. 산업기사"}, {"id": "machine_0181", "img": "q/machine/0181.webp", "ans": 3, "page": 124, "q": 37, "diff": 5, "src": "90. 96. 98. 00. 기사, 81. 83. 89. 00. 02.11. 산업기사"}, {"id": "machine_0182", "img": "q/machine/0182.webp", "ans": 4, "page": 125, "q": 38, "diff": 2, "src": "93.03. 12.산업기사"}, {"id": "machine_0183", "img": "q/machine/0183.webp", "ans": 2, "page": 125, "q": 39, "diff": 0, "src": ""}, {"id": "machine_0184", "img": "q/machine/0184.webp", "ans": 1, "page": 126, "q": 40, "diff": 1, "src": "85. 88. 93. 02.15. 기사"}, {"id": "machine_0185", "img": "q/machine/0185.webp", "ans": 1, "page": 126, "q": 41, "diff": 0, "src": ""}, {"id": "machine_0186", "img": "q/machine/0186.webp", "ans": 4, "page": 126, "q": 42, "diff": 3, "src": "90.95. 05.15. 기사, 80. 85. 96. 산업기사"}, {"id": "machine_0187", "img": "q/machine/0187.webp", "ans": 4, "page": 127, "q": 43, "diff": 4, "src": "06. 08. 기사, 96. 98.10.12.15. 산업기사"}, {"id": "machine_0188", "img": "q/machine/0188.webp", "ans": 2, "page": 127, "q": 44, "diff": 3, "src": "68.82.83.기사"}, {"id": "machine_0189", "img": "q/machine/0189.webp", "ans": 2, "page": 127, "q": 45, "diff": 1, "src": "77. 78. 99. 산업기사"}, {"id": "machine_0190", "img": "q/machine/0190.webp", "ans": 3, "page": 128, "q": 46, "diff": 0, "src": ""}, {"id": "machine_0191", "img": "q/machine/0191.webp", "ans": 1, "page": 128, "q": 47, "diff": 1, "src": "81. 88.20. 산업기사, ®: 82. 83. 93. 산업기사"}, {"id": "machine_0192", "img": "q/machine/0192.webp", "ans": 1, "page": 129, "q": 48, "diff": 4, "src": "80. 84. 94. 산업기사, ®: 77. 92. 95. 기사"}, {"id": "machine_0193", "img": "q/machine/0193.webp", "ans": 3, "page": 129, "q": 49, "diff": 3, "src": "85. 88. 94.98. 05. 기사, ® : 91.95. 기사, 86. 92. 98. 산업기사"}, {"id": "machine_0194", "img": "q/machine/0194.webp", "ans": 3, "page": 129, "q": 50, "diff": 0, "src": ""}, {"id": "machine_0195", "img": "q/machine/0195.webp", "ans": 3, "page": 130, "q": 52, "diff": 1, "src": ""}, {"id": "machine_0196", "img": "q/machine/0196.webp", "ans": 2, "page": 130, "q": 53, "diff": 0, "src": ""}, {"id": "machine_0197", "img": "q/machine/0197.webp", "ans": 4, "page": 130, "q": 54, "diff": 5, "src": "77. 83. 94. 96. 98. 기사"}, {"id": "machine_0198", "img": "q/machine/0198.webp", "ans": 3, "page": 130, "q": 55, "diff": 4, "src": ""}, {"id": "machine_0199", "img": "q/machine/0199.webp", "ans": 3, "page": 131, "q": 56, "diff": 3, "src": "89. 97. 기사, 83. 86.91.96. 산업기사, ®: 94. 산업기사"}, {"id": "machine_0200", "img": "q/machine/0200.webp", "ans": 3, "page": 131, "q": 57, "diff": 3, "src": "03. 기사"}, {"id": "machine_0201", "img": "q/machine/0201.webp", "ans": 4, "page": 131, "q": 58, "diff": 5, "src": "79.85. 90.96.98. 기사"}, {"id": "machine_0202", "img": "q/machine/0202.webp", "ans": 3, "page": 131, "q": 59, "diff": 0, "src": ""}, {"id": "machine_0203", "img": "q/machine/0203.webp", "ans": 4, "page": 131, "q": 60, "diff": 2, "src": "80. 87. 90. 95. 산업기사"}, {"id": "machine_0204", "img": "q/machine/0204.webp", "ans": 2, "page": 132, "q": 61, "diff": 1, "src": "82. 84.93. 산업기사"}, {"id": "machine_0205", "img": "q/machine/0205.webp", "ans": 4, "page": 133, "q": 62, "diff": 0, "src": ""}, {"id": "machine_0206", "img": "q/machine/0206.webp", "ans": 2, "page": 133, "q": 63, "diff": 1, "src": "96. 기사"}, {"id": "machine_0207", "img": "q/machine/0207.webp", "ans": 4, "page": 133, "q": 65, "diff": 0, "src": ""}, {"id": "machine_0208", "img": "q/machine/0208.webp", "ans": 3, "page": 135, "q": 69, "diff": 0, "src": ""}, {"id": "machine_0209", "img": "q/machine/0209.webp", "ans": 1, "page": 135, "q": 70, "diff": 1, "src": ""}, {"id": "machine_0210", "img": "q/machine/0210.webp", "ans": 4, "page": 135, "q": 71, "diff": 0, "src": ""}, {"id": "machine_0211", "img": "q/machine/0211.webp", "ans": 3, "page": 136, "q": 72, "diff": 5, "src": ""}, {"id": "machine_0212", "img": "q/machine/0212.webp", "ans": 1, "page": 136, "q": 73, "diff": 1, "src": ""}, {"id": "machine_0213", "img": "q/machine/0213.webp", "ans": 3, "page": 136, "q": 74, "diff": 2, "src": "83. 97. 09. 기사, 16. 산업기사"}, {"id": "machine_0214", "img": "q/machine/0214.webp", "ans": 4, "page": 137, "q": 75, "diff": 0, "src": ""}, {"id": "machine_0215", "img": "q/machine/0215.webp", "ans": 3, "page": 137, "q": 76, "diff": 0, "src": ""}, {"id": "machine_0216", "img": "q/machine/0216.webp", "ans": 1, "page": 137, "q": 77, "diff": 0, "src": ""}, {"id": "machine_0217", "img": "q/machine/0217.webp", "ans": 2, "page": 137, "q": 78, "diff": 0, "src": ""}, {"id": "machine_0218", "img": "q/machine/0218.webp", "ans": 3, "page": 137, "q": 79, "diff": 0, "src": ""}, {"id": "machine_0219", "img": "q/machine/0219.webp", "ans": 1, "page": 138, "q": 80, "diff": 2, "src": "78. 90. 93. 05. 25. 산업기사"}, {"id": "machine_0220", "img": "q/machine/0220.webp", "ans": 2, "page": 138, "q": 81, "diff": 1, "src": "93. 01. 기사"}, {"id": "machine_0221", "img": "q/machine/0221.webp", "ans": 3, "page": 138, "q": 82, "diff": 0, "src": "83.92. 00. 산업기사"}, {"id": "machine_0222", "img": "q/machine/0222.webp", "ans": 4, "page": 138, "q": 83, "diff": 3, "src": "10.11. 기사, 82. 83. 97. 25. 산업기사"}, {"id": "machine_0223", "img": "q/machine/0223.webp", "ans": 2, "page": 139, "q": 84, "diff": 1, "src": ""}, {"id": "machine_0224", "img": "q/machine/0224.webp", "ans": 2, "page": 139, "q": 85, "diff": 1, "src": "98. 기사"}, {"id": "machine_0225", "img": "q/machine/0225.webp", "ans": 1, "page": 139, "q": 86, "diff": 0, "src": ""}, {"id": "machine_0226", "img": "q/machine/0226.webp", "ans": 4, "page": 139, "q": 87, "diff": 2, "src": "80. 85.98. 00. 산업기사"}, {"id": "machine_0227", "img": "q/machine/0227.webp", "ans": 2, "page": 140, "q": 88, "diff": 3, "src": "95. 기사, 82. 83.91. 95. 산업기사"}, {"id": "machine_0228", "img": "q/machine/0228.webp", "ans": 4, "page": 140, "q": 89, "diff": 0, "src": ""}, {"id": "machine_0229", "img": "q/machine/0229.webp", "ans": 1, "page": 142, "q": 90, "diff": 1, "src": "78. 산업기사, ® : 77. 산업기사"}, {"id": "machine_0230", "img": "q/machine/0230.webp", "ans": 2, "page": 143, "q": 91, "diff": 0, "src": ""}, {"id": "machine_0231", "img": "q/machine/0231.webp", "ans": 4, "page": 143, "q": 92, "diff": 0, "src": "98. 기사, 82. 83. 93. 산업기사"}, {"id": "machine_0232", "img": "q/machine/0232.webp", "ans": 4, "page": 143, "q": 93, "diff": 3, "src": "80. 91. 05. 기사, 91.10.11. 산업기사"}, {"id": "machine_0233", "img": "q/machine/0233.webp", "ans": 1, "page": 144, "q": 94, "diff": 2, "src": "92.93.11.기사, 11.산업기사"}, {"id": "machine_0234", "img": "q/machine/0234.webp", "ans": 2, "page": 144, "q": 95, "diff": 5, "src": "82. 84. 94. 99. 03. 05.11. 20. 기사, 82. 83. 86. 91. 95. 산업기사"}, {"id": "machine_0235", "img": "q/machine/0235.webp", "ans": 2, "page": 144, "q": 96, "diff": 2, "src": ""}, {"id": "machine_0236", "img": "q/machine/0236.webp", "ans": 2, "page": 145, "q": 97, "diff": 0, "src": ""}, {"id": "machine_0237", "img": "q/machine/0237.webp", "ans": 4, "page": 145, "q": 98, "diff": 0, "src": ""}, {"id": "machine_0238", "img": "q/machine/0238.webp", "ans": 2, "page": 145, "q": 99, "diff": 1, "src": ""}, {"id": "machine_0239", "img": "q/machine/0239.webp", "ans": 3, "page": 145, "q": 100, "diff": 5, "src": "69. 79. 85. 88. 90. 93. 96. 기사, 85. 93. 산업기사, ⑶ : 96. 기사"}, {"id": "machine_0240", "img": "q/machine/0240.webp", "ans": 2, "page": 146, "q": 101, "diff": 0, "src": ""}, {"id": "machine_0241", "img": "q/machine/0241.webp", "ans": 3, "page": 146, "q": 102, "diff": 0, "src": "79. 기사, 76. 90. 98. 산업기사"}, {"id": "machine_0242", "img": "q/machine/0242.webp", "ans": 3, "page": 146, "q": 103, "diff": 1, "src": "83.95.산업기사"}, {"id": "machine_0243", "img": "q/machine/0243.webp", "ans": 4, "page": 147, "q": 104, "diff": 1, "src": "95. 기사，76. 산업기사"}, {"id": "machine_0244", "img": "q/machine/0244.webp", "ans": 1, "page": 147, "q": 105, "diff": 4, "src": "86. 90. 96. 00. 기사"}, {"id": "machine_0245", "img": "q/machine/0245.webp", "ans": 4, "page": 147, "q": 106, "diff": 2, "src": "98. 09.10. 25. 기사"}, {"id": "machine_0246", "img": "q/machine/0246.webp", "ans": 4, "page": 148, "q": 107, "diff": 1, "src": "79. 94. 기사, 78. 산업기사"}, {"id": "machine_0247", "img": "q/machine/0247.webp", "ans": 1, "page": 148, "q": 108, "diff": 5, "src": ""}, {"id": "machine_0248", "img": "q/machine/0248.webp", "ans": 1, "page": 148, "q": 109, "diff": 5, "src": ""}, {"id": "machine_0249", "img": "q/machine/0249.webp", "ans": 3, "page": 149, "q": 110, "diff": 1, "src": "00. 기사, 83. 산업기사"}, {"id": "machine_0250", "img": "q/machine/0250.webp", "ans": 4, "page": 149, "q": 112, "diff": 3, "src": "70. 01.11. 기사, 89. 97. 산업기사"}, {"id": "machine_0251", "img": "q/machine/0251.webp", "ans": 2, "page": 149, "q": 113, "diff": 1, "src": "93. 기사, 76. 산업기사"}, {"id": "machine_0252", "img": "q/machine/0252.webp", "ans": 4, "page": 151, "q": 114, "diff": 5, "src": ""}, {"id": "machine_0253", "img": "q/machine/0253.webp", "ans": 2, "page": 151, "q": 115, "diff": 1, "src": "68. 91. 산업기사 ® 05. 산업기사"}, {"id": "machine_0254", "img": "q/machine/0254.webp", "ans": 2, "page": 152, "q": 116, "diff": 1, "src": "20. 기사"}, {"id": "machine_0255", "img": "q/machine/0255.webp", "ans": 3, "page": 152, "q": 117, "diff": 0, "src": "81. 83.99. 산업기사"}, {"id": "machine_0256", "img": "q/machine/0256.webp", "ans": 1, "page": 152, "q": 118, "diff": 3, "src": "89. 기사, 80. 82. 88. 98. 00. 산업기사"}, {"id": "machine_0257", "img": "q/machine/0257.webp", "ans": 1, "page": 153, "q": 119, "diff": 2, "src": ""}, {"id": "machine_0258", "img": "q/machine/0258.webp", "ans": 1, "page": 153, "q": 120, "diff": 0, "src": "03.18. 기사, 78. 82. 94.10.12. 산업기사"}, {"id": "machine_0259", "img": "q/machine/0259.webp", "ans": 3, "page": 153, "q": 121, "diff": 0, "src": ""}, {"id": "machine_0260", "img": "q/machine/0260.webp", "ans": 2, "page": 153, "q": 122, "diff": 1, "src": "03. 기사"}, {"id": "machine_0261", "img": "q/machine/0261.webp", "ans": 2, "page": 154, "q": 123, "diff": 1, "src": "03. 기사, 89. 산업기사, 金 : 95. 기사"}, {"id": "machine_0262", "img": "q/machine/0262.webp", "ans": 4, "page": 154, "q": 124, "diff": 1, "src": "95.12. 기사"}, {"id": "machine_0263", "img": "q/machine/0263.webp", "ans": 3, "page": 154, "q": 125, "diff": 0, "src": "81.82. 83.94. 산업기사"}, {"id": "machine_0264", "img": "q/machine/0264.webp", "ans": 1, "page": 155, "q": 126, "diff": 3, "src": "70.77.92.93. 기사"}, {"id": "machine_0265", "img": "q/machine/0265.webp", "ans": 2, "page": 155, "q": 127, "diff": 4, "src": "82. 84. 96. 05. 기사, ©: 70. 89. 산업기사"}, {"id": "machine_0266", "img": "q/machine/0266.webp", "ans": 4, "page": 155, "q": 128, "diff": 1, "src": "78.94. 산업기사"}, {"id": "machine_0267", "img": "q/machine/0267.webp", "ans": 2, "page": 156, "q": 129, "diff": 0, "src": "99. 산업기사"}, {"id": "machine_0268", "img": "q/machine/0268.webp", "ans": 3, "page": 156, "q": 130, "diff": 1, "src": "97. 산업기사, ® : 92. 산업기사"}, {"id": "machine_0269", "img": "q/machine/0269.webp", "ans": 2, "page": 182, "q": 3, "diff": 3, "src": "98. 01. 기사，67. 75. 76. 산업기사"}, {"id": "machine_0270", "img": "q/machine/0270.webp", "ans": 2, "page": 183, "q": 7, "diff": 2, "src": "67. 77. 86.94. 산업기사"}, {"id": "machine_0271", "img": "q/machine/0271.webp", "ans": 4, "page": 184, "q": 9, "diff": 0, "src": ""}, {"id": "machine_0272", "img": "q/machine/0272.webp", "ans": 2, "page": 184, "q": 10, "diff": 1, "src": "96. 기사"}, {"id": "machine_0273", "img": "q/machine/0273.webp", "ans": 3, "page": 184, "q": 12, "diff": 5, "src": ""}, {"id": "machine_0274", "img": "q/machine/0274.webp", "ans": 2, "page": 184, "q": 13, "diff": 1, "src": ""}, {"id": "machine_0275", "img": "q/machine/0275.webp", "ans": 2, "page": 185, "q": 14, "diff": 2, "src": "77.99. 기사"}, {"id": "machine_0276", "img": "q/machine/0276.webp", "ans": 1, "page": 186, "q": 15, "diff": 1, "src": "96. 03. 기사"}, {"id": "machine_0277", "img": "q/machine/0277.webp", "ans": 4, "page": 186, "q": 16, "diff": 4, "src": "83. 86. 95. 00. 05. 기사"}, {"id": "machine_0278", "img": "q/machine/0278.webp", "ans": 3, "page": 186, "q": 17, "diff": 1, "src": ""}, {"id": "machine_0279", "img": "q/machine/0279.webp", "ans": 1, "page": 186, "q": 18, "diff": 3, "src": ""}, {"id": "machine_0280", "img": "q/machine/0280.webp", "ans": 3, "page": 188, "q": 21, "diff": 0, "src": ""}, {"id": "machine_0281", "img": "q/machine/0281.webp", "ans": 4, "page": 188, "q": 22, "diff": 1, "src": "95. 기사"}, {"id": "machine_0282", "img": "q/machine/0282.webp", "ans": 4, "page": 189, "q": 23, "diff": 1, "src": "01.05. 산업기사"}, {"id": "machine_0283", "img": "q/machine/0283.webp", "ans": 3, "page": 189, "q": 24, "diff": 1, "src": ""}, {"id": "machine_0284", "img": "q/machine/0284.webp", "ans": 4, "page": 190, "q": 25, "diff": 0, "src": "03.산업기사"}, {"id": "machine_0285", "img": "q/machine/0285.webp", "ans": 3, "page": 190, "q": 26, "diff": 0, "src": "92.산업기사"}, {"id": "machine_0286", "img": "q/machine/0286.webp", "ans": 2, "page": 190, "q": 27, "diff": 1, "src": "97. 기사, 12. 산업기사"}, {"id": "machine_0287", "img": "q/machine/0287.webp", "ans": 2, "page": 192, "q": 34, "diff": 3, "src": ""}, {"id": "machine_0288", "img": "q/machine/0288.webp", "ans": 3, "page": 192, "q": 35, "diff": 0, "src": ""}, {"id": "machine_0289", "img": "q/machine/0289.webp", "ans": 3, "page": 192, "q": 36, "diff": 1, "src": ""}, {"id": "machine_0290", "img": "q/machine/0290.webp", "ans": 3, "page": 192, "q": 37, "diff": 1, "src": ""}, {"id": "machine_0291", "img": "q/machine/0291.webp", "ans": 4, "page": 193, "q": 38, "diff": 0, "src": ""}, {"id": "machine_0292", "img": "q/machine/0292.webp", "ans": 1, "page": 193, "q": 39, "diff": 0, "src": ""}, {"id": "machine_0293", "img": "q/machine/0293.webp", "ans": 2, "page": 193, "q": 40, "diff": 0, "src": ""}, {"id": "machine_0294", "img": "q/machine/0294.webp", "ans": 4, "page": 194, "q": 41, "diff": 0, "src": ""}, {"id": "machine_0295", "img": "q/machine/0295.webp", "ans": 3, "page": 194, "q": 42, "diff": 1, "src": "87.91.03. 15.산업기사"}, {"id": "machine_0296", "img": "q/machine/0296.webp", "ans": 2, "page": 194, "q": 43, "diff": 0, "src": ""}, {"id": "machine_0297", "img": "q/machine/0297.webp", "ans": 2, "page": 194, "q": 44, "diff": 0, "src": ""}, {"id": "machine_0298", "img": "q/machine/0298.webp", "ans": 1, "page": 195, "q": 45, "diff": 0, "src": "88. 93. 98. 기사, 81. 82. 85. 89. 93. 산업기사"}, {"id": "machine_0299", "img": "q/machine/0299.webp", "ans": 1, "page": 195, "q": 46, "diff": 0, "src": ""}, {"id": "machine_0300", "img": "q/machine/0300.webp", "ans": 3, "page": 195, "q": 47, "diff": 0, "src": "96. 03. 산업기사"}, {"id": "machine_0301", "img": "q/machine/0301.webp", "ans": 3, "page": 195, "q": 48, "diff": 3, "src": ""}, {"id": "machine_0302", "img": "q/machine/0302.webp", "ans": 3, "page": 197, "q": 49, "diff": 0, "src": ""}, {"id": "machine_0303", "img": "q/machine/0303.webp", "ans": 1, "page": 197, "q": 51, "diff": 5, "src": ""}, {"id": "machine_0304", "img": "q/machine/0304.webp", "ans": 2, "page": 197, "q": 52, "diff": 0, "src": ""}, {"id": "machine_0305", "img": "q/machine/0305.webp", "ans": 1, "page": 198, "q": 53, "diff": 0, "src": ""}, {"id": "machine_0306", "img": "q/machine/0306.webp", "ans": 1, "page": 198, "q": 54, "diff": 2, "src": "79. 가사, 89.95. 산업기사"}, {"id": "machine_0307", "img": "q/machine/0307.webp", "ans": 2, "page": 198, "q": 55, "diff": 5, "src": "83. 84. 90. 07. 기사, 83. 90. 94. 98. 03.11. 산업기사, ® : 85. 94. 기사"}, {"id": "machine_0308", "img": "q/machine/0308.webp", "ans": 3, "page": 198, "q": 56, "diff": 0, "src": ""}, {"id": "machine_0309", "img": "q/machine/0309.webp", "ans": 3, "page": 199, "q": 57, "diff": 1, "src": "87. 기사, 87.90. 산업기사"}, {"id": "machine_0310", "img": "q/machine/0310.webp", "ans": 1, "page": 199, "q": 58, "diff": 1, "src": "97. 기사, 85. 25. 산업기사"}, {"id": "machine_0311", "img": "q/machine/0311.webp", "ans": 4, "page": 199, "q": 59, "diff": 0, "src": "92. 기사, 76. 86. 94. 97. 산업기사"}, {"id": "machine_0312", "img": "q/machine/0312.webp", "ans": 1, "page": 201, "q": 60, "diff": 0, "src": ""}, {"id": "machine_0313", "img": "q/machine/0313.webp", "ans": 1, "page": 201, "q": 61, "diff": 0, "src": ""}, {"id": "machine_0314", "img": "q/machine/0314.webp", "ans": 4, "page": 202, "q": 63, "diff": 0, "src": ""}, {"id": "machine_0315", "img": "q/machine/0315.webp", "ans": 3, "page": 202, "q": 64, "diff": 0, "src": "89. 산업기사"}, {"id": "machine_0316", "img": "q/machine/0316.webp", "ans": 3, "page": 202, "q": 65, "diff": 1, "src": "03. 기사 92. 93. 산업기사"}, {"id": "machine_0317", "img": "q/machine/0317.webp", "ans": 4, "page": 202, "q": 66, "diff": 1, "src": "92.99. 산업기사"}, {"id": "machine_0318", "img": "q/machine/0318.webp", "ans": 2, "page": 203, "q": 67, "diff": 2, "src": "91.98.18. 25. 기사"}, {"id": "machine_0319", "img": "q/machine/0319.webp", "ans": 4, "page": 203, "q": 68, "diff": 2, "src": "00.02.04.기사, 81.11.산업기사"}, {"id": "machine_0320", "img": "q/machine/0320.webp", "ans": 4, "page": 203, "q": 69, "diff": 2, "src": "82. 98. 00. 01. 03. 산업기사"}, {"id": "machine_0321", "img": "q/machine/0321.webp", "ans": 3, "page": 203, "q": 70, "diff": 2, "src": "86.91.기사"}, {"id": "machine_0322", "img": "q/machine/0322.webp", "ans": 2, "page": 204, "q": 71, "diff": 0, "src": ""}, {"id": "machine_0323", "img": "q/machine/0323.webp", "ans": 2, "page": 204, "q": 72, "diff": 0, "src": ""}, {"id": "machine_0324", "img": "q/machine/0324.webp", "ans": 3, "page": 205, "q": 73, "diff": 1, "src": "83.92. 산업기사"}, {"id": "machine_0325", "img": "q/machine/0325.webp", "ans": 3, "page": 205, "q": 74, "diff": 4, "src": ""}, {"id": "machine_0326", "img": "q/machine/0326.webp", "ans": 4, "page": 206, "q": 75, "diff": 4, "src": ""}, {"id": "machine_0327", "img": "q/machine/0327.webp", "ans": 1, "page": 206, "q": 76, "diff": 0, "src": ""}, {"id": "machine_0328", "img": "q/machine/0328.webp", "ans": 4, "page": 206, "q": 77, "diff": 0, "src": ""}, {"id": "machine_0329", "img": "q/machine/0329.webp", "ans": 2, "page": 206, "q": 78, "diff": 0, "src": ""}, {"id": "machine_0330", "img": "q/machine/0330.webp", "ans": 2, "page": 207, "q": 79, "diff": 2, "src": "89. 94. 20. 산업기사"}, {"id": "machine_0331", "img": "q/machine/0331.webp", "ans": 4, "page": 207, "q": 80, "diff": 1, "src": "92. 기사"}, {"id": "machine_0332", "img": "q/machine/0332.webp", "ans": 4, "page": 208, "q": 81, "diff": 0, "src": ""}, {"id": "machine_0333", "img": "q/machine/0333.webp", "ans": 2, "page": 208, "q": 82, "diff": 2, "src": "03. 기사, 83. 85. 93. 산업기사, 節 : 94. 산업기사"}, {"id": "machine_0334", "img": "q/machine/0334.webp", "ans": 1, "page": 208, "q": 83, "diff": 4, "src": "77. 97. 기사, 75. 76. 산업기사, ® : 82. 기사"}, {"id": "machine_0335", "img": "q/machine/0335.webp", "ans": 1, "page": 208, "q": 84, "diff": 1, "src": "87.94. 산업기사"}, {"id": "machine_0336", "img": "q/machine/0336.webp", "ans": 1, "page": 208, "q": 85, "diff": 5, "src": "86. 91. 98. 00.11. 기사, 89. 산업기사, ® : 77. 78. 89.18. 산업기사"}, {"id": "machine_0337", "img": "q/machine/0337.webp", "ans": 3, "page": 209, "q": 86, "diff": 0, "src": ""}, {"id": "machine_0338", "img": "q/machine/0338.webp", "ans": 2, "page": 209, "q": 87, "diff": 3, "src": "82.97. 산업기사, ®: 87. 94. 기사"}, {"id": "machine_0339", "img": "q/machine/0339.webp", "ans": 2, "page": 210, "q": 88, "diff": 1, "src": ""}, {"id": "machine_0340", "img": "q/machine/0340.webp", "ans": 3, "page": 210, "q": 89, "diff": 5, "src": ""}, {"id": "machine_0341", "img": "q/machine/0341.webp", "ans": 4, "page": 210, "q": 90, "diff": 1, "src": "77. 88. 89. 93. 94. 기사, 78. 92. 98. 산업기사"}, {"id": "machine_0342", "img": "q/machine/0342.webp", "ans": 3, "page": 210, "q": 91, "diff": 1, "src": "82. 96. 98.12. 산업기사"}, {"id": "machine_0343", "img": "q/machine/0343.webp", "ans": 1, "page": 211, "q": 92, "diff": 0, "src": "80. 기사, 89. 산업기사"}, {"id": "machine_0344", "img": "q/machine/0344.webp", "ans": 3, "page": 211, "q": 93, "diff": 1, "src": "02.03.기사"}, {"id": "machine_0345", "img": "q/machine/0345.webp", "ans": 2, "page": 211, "q": 94, "diff": 3, "src": ""}, {"id": "machine_0346", "img": "q/machine/0346.webp", "ans": 3, "page": 211, "q": 95, "diff": 2, "src": "80. 84. 98. 00. 산업기사"}, {"id": "machine_0347", "img": "q/machine/0347.webp", "ans": 3, "page": 212, "q": 96, "diff": 1, "src": "98. 기사"}, {"id": "machine_0348", "img": "q/machine/0348.webp", "ans": 3, "page": 212, "q": 97, "diff": 0, "src": "99.01.기사"}, {"id": "machine_0349", "img": "q/machine/0349.webp", "ans": 2, "page": 214, "q": 99, "diff": 0, "src": ""}, {"id": "machine_0350", "img": "q/machine/0350.webp", "ans": 4, "page": 215, "q": 102, "diff": 1, "src": "93. 기사"}, {"id": "machine_0351", "img": "q/machine/0351.webp", "ans": 2, "page": 216, "q": 106, "diff": 0, "src": "99. 03. 산업기사"}, {"id": "machine_0352", "img": "q/machine/0352.webp", "ans": 4, "page": 216, "q": 107, "diff": 2, "src": "94. 기사, 81. 82. 05. 산업기사"}, {"id": "machine_0353", "img": "q/machine/0353.webp", "ans": 4, "page": 216, "q": 108, "diff": 1, "src": "97.11.기사"}, {"id": "machine_0354", "img": "q/machine/0354.webp", "ans": 1, "page": 217, "q": 109, "diff": 4, "src": "82.83.96.98.기사"}, {"id": "machine_0355", "img": "q/machine/0355.webp", "ans": 3, "page": 217, "q": 110, "diff": 2, "src": "97. 기사, ® ： 80. 기사"}, {"id": "machine_0356", "img": "q/machine/0356.webp", "ans": 2, "page": 217, "q": 111, "diff": 0, "src": ""}, {"id": "machine_0357", "img": "q/machine/0357.webp", "ans": 3, "page": 218, "q": 112, "diff": 0, "src": "88. 98. 03. 산업기사"}, {"id": "machine_0358", "img": "q/machine/0358.webp", "ans": 4, "page": 218, "q": 113, "diff": 0, "src": ""}, {"id": "machine_0359", "img": "q/machine/0359.webp", "ans": 3, "page": 218, "q": 114, "diff": 1, "src": "94.03.기사,® ： 11.산업기사"}, {"id": "machine_0360", "img": "q/machine/0360.webp", "ans": 3, "page": 219, "q": 115, "diff": 3, "src": "80. 84.92. 기사"}, {"id": "machine_0361", "img": "q/machine/0361.webp", "ans": 2, "page": 219, "q": 116, "diff": 0, "src": ""}, {"id": "machine_0362", "img": "q/machine/0362.webp", "ans": 2, "page": 219, "q": 117, "diff": 3, "src": "83. 기사, 83. 90. 94. 97. 산업기사"}, {"id": "machine_0363", "img": "q/machine/0363.webp", "ans": 3, "page": 220, "q": 119, "diff": 3, "src": "89. 기사, 88. 98. 00. 01. 산업기사"}, {"id": "machine_0364", "img": "q/machine/0364.webp", "ans": 1, "page": 220, "q": 121, "diff": 0, "src": ""}, {"id": "machine_0365", "img": "q/machine/0365.webp", "ans": 1, "page": 220, "q": 122, "diff": 1, "src": "03. 기사, 92. 01. 산업기사"}, {"id": "machine_0366", "img": "q/machine/0366.webp", "ans": 2, "page": 221, "q": 124, "diff": 0, "src": "85.91.95. 08. 산업기사"}, {"id": "machine_0367", "img": "q/machine/0367.webp", "ans": 2, "page": 223, "q": 125, "diff": 2, "src": "96. 99.16. 25. 산업기사"}, {"id": "machine_0368", "img": "q/machine/0368.webp", "ans": 4, "page": 223, "q": 128, "diff": 1, "src": "99.11.기사"}, {"id": "machine_0369", "img": "q/machine/0369.webp", "ans": 4, "page": 223, "q": 129, "diff": 1, "src": "01. 09. 기사, 94. 산업기사"}, {"id": "machine_0370", "img": "q/machine/0370.webp", "ans": 2, "page": 224, "q": 130, "diff": 1, "src": ""}, {"id": "machine_0371", "img": "q/machine/0371.webp", "ans": 3, "page": 225, "q": 135, "diff": 4, "src": "76. 92. 97.11. 25. 기사, 90. 93. 94. 03. 05. 산업기사 證 05. 기사"}, {"id": "machine_0372", "img": "q/machine/0372.webp", "ans": 1, "page": 225, "q": 136, "diff": 1, "src": "80.93.산업기사"}, {"id": "machine_0373", "img": "q/machine/0373.webp", "ans": 3, "page": 225, "q": 137, "diff": 5, "src": "77. 86. 91. 99. 기사, 75. 92. 98. 산업기사"}, {"id": "machine_0374", "img": "q/machine/0374.webp", "ans": 4, "page": 226, "q": 138, "diff": 0, "src": "93.산업기사"}, {"id": "machine_0375", "img": "q/machine/0375.webp", "ans": 3, "page": 226, "q": 139, "diff": 0, "src": "88.94. 산업기사"}, {"id": "machine_0376", "img": "q/machine/0376.webp", "ans": 4, "page": 226, "q": 140, "diff": 1, "src": ""}, {"id": "machine_0377", "img": "q/machine/0377.webp", "ans": 1, "page": 226, "q": 141, "diff": 0, "src": ""}, {"id": "machine_0378", "img": "q/machine/0378.webp", "ans": 3, "page": 227, "q": 142, "diff": 0, "src": ""}, {"id": "machine_0379", "img": "q/machine/0379.webp", "ans": 4, "page": 227, "q": 143, "diff": 0, "src": "93.산업기사"}, {"id": "machine_0380", "img": "q/machine/0380.webp", "ans": 3, "page": 227, "q": 144, "diff": 4, "src": "78. 80. 86. 91. 96. 산업기사, ®: 77. 92. 05.18. 기사"}, {"id": "machine_0381", "img": "q/machine/0381.webp", "ans": 2, "page": 227, "q": 145, "diff": 1, "src": "79. 89. 09. 산업기사"}, {"id": "machine_0382", "img": "q/machine/0382.webp", "ans": 2, "page": 227, "q": 146, "diff": 2, "src": "85.97.16.기사"}, {"id": "machine_0383", "img": "q/machine/0383.webp", "ans": 2, "page": 228, "q": 147, "diff": 0, "src": "93.12. 산업기사"}, {"id": "machine_0384", "img": "q/machine/0384.webp", "ans": 1, "page": 228, "q": 148, "diff": 0, "src": "96.산업기사"}, {"id": "machine_0385", "img": "q/machine/0385.webp", "ans": 2, "page": 228, "q": 149, "diff": 1, "src": "87. 94. 01. 산업기사"}, {"id": "machine_0386", "img": "q/machine/0386.webp", "ans": 4, "page": 228, "q": 150, "diff": 1, "src": "01. 기사, 62. 산업기사"}, {"id": "machine_0387", "img": "q/machine/0387.webp", "ans": 2, "page": 229, "q": 151, "diff": 0, "src": "83. 89. 97. 05. 11. 산업기사, ®: 92. 94. 기사"}, {"id": "machine_0388", "img": "q/machine/0388.webp", "ans": 1, "page": 229, "q": 152, "diff": 1, "src": ""}, {"id": "machine_0389", "img": "q/machine/0389.webp", "ans": 4, "page": 230, "q": 155, "diff": 1, "src": "92. 98. 00. 산업기사"}, {"id": "machine_0390", "img": "q/machine/0390.webp", "ans": 2, "page": 230, "q": 156, "diff": 1, "src": "77. 99. 산업기사"}, {"id": "machine_0391", "img": "q/machine/0391.webp", "ans": 1, "page": 230, "q": 157, "diff": 0, "src": ""}, {"id": "machine_0392", "img": "q/machine/0392.webp", "ans": 4, "page": 230, "q": 158, "diff": 0, "src": "03. 기사"}, {"id": "machine_0393", "img": "q/machine/0393.webp", "ans": 1, "page": 233, "q": 159, "diff": 5, "src": "82. 83. 85. 88. 91. 92. 94. 95. 96. 97. 98. 99. 00. 01.11. 20. 산업기사"}, {"id": "machine_0394", "img": "q/machine/0394.webp", "ans": 1, "page": 233, "q": 160, "diff": 1, "src": "78. 93. 01. 산업기사"}, {"id": "machine_0395", "img": "q/machine/0395.webp", "ans": 1, "page": 233, "q": 161, "diff": 0, "src": ""}, {"id": "machine_0396", "img": "q/machine/0396.webp", "ans": 4, "page": 234, "q": 162, "diff": 1, "src": "84. 94. 97. 05. 산업기사"}, {"id": "machine_0397", "img": "q/machine/0397.webp", "ans": 4, "page": 234, "q": 165, "diff": 0, "src": ""}, {"id": "machine_0398", "img": "q/machine/0398.webp", "ans": 3, "page": 234, "q": 166, "diff": 1, "src": ""}, {"id": "machine_0399", "img": "q/machine/0399.webp", "ans": 2, "page": 235, "q": 168, "diff": 0, "src": "91. 05. 기사, 89. 98. 01. 03. 산업기사"}, {"id": "machine_0400", "img": "q/machine/0400.webp", "ans": 2, "page": 235, "q": 169, "diff": 0, "src": ""}, {"id": "machine_0401", "img": "q/machine/0401.webp", "ans": 2, "page": 236, "q": 173, "diff": 4, "src": ""}, {"id": "machine_0402", "img": "q/machine/0402.webp", "ans": 4, "page": 236, "q": 174, "diff": 1, "src": "86. 94.97.15. 산업기사"}, {"id": "machine_0403", "img": "q/machine/0403.webp", "ans": 4, "page": 236, "q": 175, "diff": 2, "src": "86. 91. 93. 95. 산업기사"}, {"id": "machine_0404", "img": "q/machine/0404.webp", "ans": 2, "page": 236, "q": 176, "diff": 0, "src": ""}, {"id": "machine_0405", "img": "q/machine/0405.webp", "ans": 3, "page": 236, "q": 177, "diff": 1, "src": ""}, {"id": "machine_0406", "img": "q/machine/0406.webp", "ans": 1, "page": 237, "q": 178, "diff": 0, "src": "98. 기사"}, {"id": "machine_0407", "img": "q/machine/0407.webp", "ans": 2, "page": 261, "q": 1, "diff": 3, "src": "85. 95. 01. 04.12. 기사® : 05. 기사"}, {"id": "machine_0408", "img": "q/machine/0408.webp", "ans": 1, "page": 261, "q": 2, "diff": 0, "src": "78.10. 기사"}, {"id": "machine_0409", "img": "q/machine/0409.webp", "ans": 3, "page": 261, "q": 3, "diff": 5, "src": ""}, {"id": "machine_0410", "img": "q/machine/0410.webp", "ans": 2, "page": 262, "q": 4, "diff": 0, "src": "85. 산업기사"}, {"id": "machine_0411", "img": "q/machine/0411.webp", "ans": 2, "page": 262, "q": 5, "diff": 4, "src": "98. 85. 기사, 85. 산업기사, ® : 11. 기사, 76. 80. 85. 산업기사"}, {"id": "machine_0412", "img": "q/machine/0412.webp", "ans": 3, "page": 262, "q": 6, "diff": 1, "src": "03. 기사"}, {"id": "machine_0413", "img": "q/machine/0413.webp", "ans": 5, "page": 262, "q": 7, "diff": 0, "src": ""}, {"id": "machine_0414", "img": "q/machine/0414.webp", "ans": 4, "page": 263, "q": 9, "diff": 0, "src": ""}, {"id": "machine_0415", "img": "q/machine/0415.webp", "ans": 4, "page": 264, "q": 10, "diff": 0, "src": ""}, {"id": "machine_0416", "img": "q/machine/0416.webp", "ans": 3, "page": 264, "q": 11, "diff": 2, "src": "79.94.02.12.산업기사"}, {"id": "machine_0417", "img": "q/machine/0417.webp", "ans": 1, "page": 265, "q": 12, "diff": 5, "src": ""}, {"id": "machine_0418", "img": "q/machine/0418.webp", "ans": 2, "page": 265, "q": 13, "diff": 0, "src": ""}, {"id": "machine_0419", "img": "q/machine/0419.webp", "ans": 3, "page": 265, "q": 14, "diff": 0, "src": ""}, {"id": "machine_0420", "img": "q/machine/0420.webp", "ans": 4, "page": 265, "q": 15, "diff": 0, "src": "92. 기사, ®：81. 산업기사"}, {"id": "machine_0421", "img": "q/machine/0421.webp", "ans": 3, "page": 266, "q": 17, "diff": 3, "src": "01. 05. 기사, 98. 00. 산업기사, ® : 77. 78. 산업기사"}, {"id": "machine_0422", "img": "q/machine/0422.webp", "ans": 2, "page": 266, "q": 18, "diff": 3, "src": "78. 85. 88. 97. 98. 20. 산업기사, © : 16. 기사, 83. 산업기사"}, {"id": "machine_0423", "img": "q/machine/0423.webp", "ans": 3, "page": 267, "q": 19, "diff": 2, "src": "76. 78.81.96. 산업기사"}, {"id": "machine_0424", "img": "q/machine/0424.webp", "ans": 1, "page": 267, "q": 20, "diff": 0, "src": ""}, {"id": "machine_0425", "img": "q/machine/0425.webp", "ans": 3, "page": 268, "q": 22, "diff": 1, "src": "82.95.00. 산업기사"}, {"id": "machine_0426", "img": "q/machine/0426.webp", "ans": 4, "page": 268, "q": 23, "diff": 3, "src": ""}, {"id": "machine_0427", "img": "q/machine/0427.webp", "ans": 1, "page": 269, "q": 24, "diff": 1, "src": "83. 기사"}, {"id": "machine_0428", "img": "q/machine/0428.webp", "ans": 4, "page": 269, "q": 25, "diff": 2, "src": "94. 03.12, 기사"}, {"id": "machine_0429", "img": "q/machine/0429.webp", "ans": 2, "page": 269, "q": 26, "diff": 1, "src": "82.88. 00. 산업기사"}, {"id": "machine_0430", "img": "q/machine/0430.webp", "ans": 2, "page": 270, "q": 27, "diff": 1, "src": ""}, {"id": "machine_0431", "img": "q/machine/0431.webp", "ans": 4, "page": 270, "q": 28, "diff": 2, "src": "92. 99.10. 기사"}, {"id": "machine_0432", "img": "q/machine/0432.webp", "ans": 3, "page": 270, "q": 29, "diff": 5, "src": ""}, {"id": "machine_0433", "img": "q/machine/0433.webp", "ans": 3, "page": 270, "q": 30, "diff": 5, "src": ""}, {"id": "machine_0434", "img": "q/machine/0434.webp", "ans": 3, "page": 271, "q": 31, "diff": 0, "src": ""}, {"id": "machine_0435", "img": "q/machine/0435.webp", "ans": 3, "page": 271, "q": 32, "diff": 0, "src": ""}, {"id": "machine_0436", "img": "q/machine/0436.webp", "ans": 4, "page": 271, "q": 33, "diff": 0, "src": ""}, {"id": "machine_0437", "img": "q/machine/0437.webp", "ans": 2, "page": 271, "q": 34, "diff": 1, "src": ""}, {"id": "machine_0438", "img": "q/machine/0438.webp", "ans": 1, "page": 272, "q": 36, "diff": 2, "src": "88. 05.12.18. 기사"}, {"id": "machine_0439", "img": "q/machine/0439.webp", "ans": 3, "page": 274, "q": 37, "diff": 1, "src": "05. 기사 79. 89. 94. 96. 00. 산업기사, ® ： 11. 산업기사"}, {"id": "machine_0440", "img": "q/machine/0440.webp", "ans": 4, "page": 274, "q": 38, "diff": 1, "src": "79.기사,11.산업기사"}, {"id": "machine_0441", "img": "q/machine/0441.webp", "ans": 3, "page": 274, "q": 39, "diff": 5, "src": "77. 85. 89. 99. 기사, 88. 99. 산업기사"}, {"id": "machine_0442", "img": "q/machine/0442.webp", "ans": 4, "page": 274, "q": 40, "diff": 1, "src": "67.92.산업기사®：05.산업기사"}, {"id": "machine_0443", "img": "q/machine/0443.webp", "ans": 1, "page": 276, "q": 45, "diff": 0, "src": ""}, {"id": "machine_0444", "img": "q/machine/0444.webp", "ans": 1, "page": 276, "q": 46, "diff": 0, "src": ""}, {"id": "machine_0445", "img": "q/machine/0445.webp", "ans": 3, "page": 276, "q": 47, "diff": 0, "src": ""}, {"id": "machine_0446", "img": "q/machine/0446.webp", "ans": 4, "page": 276, "q": 48, "diff": 1, "src": "87. 기사, 90. 산업기사"}, {"id": "machine_0447", "img": "q/machine/0447.webp", "ans": 2, "page": 277, "q": 49, "diff": 4, "src": "84. 92. 01. 기사, 16. 산업기사, ® ： 91. 기사"}, {"id": "machine_0448", "img": "q/machine/0448.webp", "ans": 4, "page": 277, "q": 50, "diff": 3, "src": ""}, {"id": "machine_0449", "img": "q/machine/0449.webp", "ans": 3, "page": 277, "q": 51, "diff": 0, "src": ""}, {"id": "machine_0450", "img": "q/machine/0450.webp", "ans": 2, "page": 277, "q": 52, "diff": 0, "src": "03. 기사"}, {"id": "machine_0451", "img": "q/machine/0451.webp", "ans": 2, "page": 279, "q": 54, "diff": 1, "src": "82. 89. 산업기사"}, {"id": "machine_0452", "img": "q/machine/0452.webp", "ans": 4, "page": 279, "q": 55, "diff": 0, "src": ""}, {"id": "machine_0453", "img": "q/machine/0453.webp", "ans": 4, "page": 280, "q": 56, "diff": 1, "src": "85.95. 산업기사"}, {"id": "machine_0454", "img": "q/machine/0454.webp", "ans": 4, "page": 280, "q": 57, "diff": 5, "src": "80. 82. 83. 84. 94. 96. 01. 기사, 85. 96. 00. 03. 05. 20. 산업기사, ® : 95. 기사"}, {"id": "machine_0455", "img": "q/machine/0455.webp", "ans": 2, "page": 280, "q": 58, "diff": 0, "src": "70.산업기사"}, {"id": "machine_0456", "img": "q/machine/0456.webp", "ans": 3, "page": 280, "q": 59, "diff": 1, "src": "76.96. 산업기사"}, {"id": "machine_0457", "img": "q/machine/0457.webp", "ans": 4, "page": 280, "q": 60, "diff": 0, "src": ""}, {"id": "machine_0458", "img": "q/machine/0458.webp", "ans": 1, "page": 281, "q": 61, "diff": 0, "src": ""}, {"id": "machine_0459", "img": "q/machine/0459.webp", "ans": 3, "page": 281, "q": 62, "diff": 0, "src": ""}, {"id": "machine_0460", "img": "q/machine/0460.webp", "ans": 4, "page": 282, "q": 63, "diff": 0, "src": ""}, {"id": "machine_0461", "img": "q/machine/0461.webp", "ans": 1, "page": 282, "q": 64, "diff": 2, "src": "86. 93.97.12. 25. 산업기사"}, {"id": "machine_0462", "img": "q/machine/0462.webp", "ans": 2, "page": 282, "q": 65, "diff": 3, "src": ""}, {"id": "machine_0463", "img": "q/machine/0463.webp", "ans": 4, "page": 282, "q": 66, "diff": 2, "src": "91.96.11.12.산업기사"}, {"id": "machine_0464", "img": "q/machine/0464.webp", "ans": 2, "page": 283, "q": 67, "diff": 0, "src": ""}, {"id": "machine_0465", "img": "q/machine/0465.webp", "ans": 2, "page": 283, "q": 68, "diff": 0, "src": ""}, {"id": "machine_0466", "img": "q/machine/0466.webp", "ans": 4, "page": 283, "q": 70, "diff": 5, "src": "83. 85. 89. 94. 00. 08.12. 20. 25. 기사, 83. 84. 89. 93. 06. 08. 산업기사"}, {"id": "machine_0467", "img": "q/machine/0467.webp", "ans": 3, "page": 283, "q": 71, "diff": 0, "src": ""}, {"id": "machine_0468", "img": "q/machine/0468.webp", "ans": 2, "page": 284, "q": 73, "diff": 2, "src": "12. 기사, 81. 84. 04. 산업기사"}, {"id": "machine_0469", "img": "q/machine/0469.webp", "ans": 2, "page": 285, "q": 74, "diff": 0, "src": ""}, {"id": "machine_0470", "img": "q/machine/0470.webp", "ans": 2, "page": 285, "q": 75, "diff": 0, "src": "01.산업기사"}, {"id": "machine_0471", "img": "q/machine/0471.webp", "ans": 2, "page": 285, "q": 76, "diff": 0, "src": "94.산업기사"}, {"id": "machine_0472", "img": "q/machine/0472.webp", "ans": 2, "page": 286, "q": 78, "diff": 1, "src": "93. 00. 산업기사"}, {"id": "machine_0473", "img": "q/machine/0473.webp", "ans": 2, "page": 286, "q": 79, "diff": 0, "src": "97.산업기사"}, {"id": "machine_0474", "img": "q/machine/0474.webp", "ans": 2, "page": 289, "q": 83, "diff": 1, "src": "85. 92. 05. 산업기사"}, {"id": "machine_0475", "img": "q/machine/0475.webp", "ans": 2, "page": 290, "q": 84, "diff": 1, "src": "81. 산업기사, ® ： 84. 기사"}, {"id": "machine_0476", "img": "q/machine/0476.webp", "ans": 2, "page": 290, "q": 85, "diff": 0, "src": ""}, {"id": "machine_0477", "img": "q/machine/0477.webp", "ans": 1, "page": 290, "q": 86, "diff": 0, "src": ""}, {"id": "machine_0478", "img": "q/machine/0478.webp", "ans": 4, "page": 290, "q": 87, "diff": 2, "src": "83. 91.95.11. 산업기사"}, {"id": "machine_0479", "img": "q/machine/0479.webp", "ans": 2, "page": 291, "q": 89, "diff": 1, "src": "01.가사"}, {"id": "machine_0480", "img": "q/machine/0480.webp", "ans": 2, "page": 291, "q": 90, "diff": 3, "src": ""}, {"id": "machine_0481", "img": "q/machine/0481.webp", "ans": 4, "page": 292, "q": 92, "diff": 1, "src": "70. 90. 96. 산업기사"}, {"id": "machine_0482", "img": "q/machine/0482.webp", "ans": 2, "page": 292, "q": 93, "diff": 1, "src": ""}, {"id": "machine_0483", "img": "q/machine/0483.webp", "ans": 1, "page": 292, "q": 94, "diff": 0, "src": "03. 산업기사"}, {"id": "machine_0484", "img": "q/machine/0484.webp", "ans": 2, "page": 292, "q": 95, "diff": 0, "src": ""}, {"id": "machine_0485", "img": "q/machine/0485.webp", "ans": 3, "page": 293, "q": 97, "diff": 1, "src": "83. 90. 96. 99. 산업기사"}, {"id": "machine_0486", "img": "q/machine/0486.webp", "ans": 4, "page": 293, "q": 98, "diff": 0, "src": ""}, {"id": "machine_0487", "img": "q/machine/0487.webp", "ans": 4, "page": 294, "q": 101, "diff": 3, "src": ""}, {"id": "machine_0488", "img": "q/machine/0488.webp", "ans": 1, "page": 294, "q": 102, "diff": 1, "src": "93.기사, 77.91.96.산업기사"}, {"id": "machine_0489", "img": "q/machine/0489.webp", "ans": 3, "page": 294, "q": 103, "diff": 2, "src": "78. 95. 산업기사, ® : 77. 기사, 05. 산업기사"}, {"id": "machine_0490", "img": "q/machine/0490.webp", "ans": 1, "page": 294, "q": 104, "diff": 1, "src": "78. 기사, 82. 83. 97.12. 산업기사"}, {"id": "machine_0491", "img": "q/machine/0491.webp", "ans": 1, "page": 295, "q": 105, "diff": 1, "src": "79. 기사"}, {"id": "machine_0492", "img": "q/machine/0492.webp", "ans": 1, "page": 295, "q": 106, "diff": 1, "src": "81. 83. 94. 산업기사"}, {"id": "machine_0493", "img": "q/machine/0493.webp", "ans": 1, "page": 296, "q": 108, "diff": 0, "src": "93. 산업기사"}, {"id": "machine_0494", "img": "q/machine/0494.webp", "ans": 1, "page": 297, "q": 109, "diff": 1, "src": "02.기사"}, {"id": "machine_0495", "img": "q/machine/0495.webp", "ans": 2, "page": 297, "q": 110, "diff": 1, "src": "85. 88. 95.15. 산업기사"}, {"id": "machine_0496", "img": "q/machine/0496.webp", "ans": 4, "page": 297, "q": 111, "diff": 0, "src": ""}, {"id": "machine_0497", "img": "q/machine/0497.webp", "ans": 1, "page": 298, "q": 112, "diff": 2, "src": "79. 기사, 91. 98. 산업기사"}, {"id": "machine_0498", "img": "q/machine/0498.webp", "ans": 3, "page": 298, "q": 113, "diff": 1, "src": "87.93.산업기사"}, {"id": "machine_0499", "img": "q/machine/0499.webp", "ans": 1, "page": 298, "q": 114, "diff": 0, "src": "97. 기사, 88. 95. 99. 산업기사"}, {"id": "machine_0500", "img": "q/machine/0500.webp", "ans": 1, "page": 298, "q": 115, "diff": 1, "src": "87. 91. 95. 산업기사"}, {"id": "machine_0501", "img": "q/machine/0501.webp", "ans": 3, "page": 299, "q": 116, "diff": 4, "src": "84. 92. 99. 02. 03. 07. 09.12. 산업기사"}, {"id": "machine_0502", "img": "q/machine/0502.webp", "ans": 3, "page": 299, "q": 117, "diff": 0, "src": "00.산업기사"}, {"id": "machine_0503", "img": "q/machine/0503.webp", "ans": 4, "page": 299, "q": 118, "diff": 2, "src": "96. 01. 05. 기사"}, {"id": "machine_0504", "img": "q/machine/0504.webp", "ans": 2, "page": 300, "q": 121, "diff": 1, "src": ""}, {"id": "machine_0505", "img": "q/machine/0505.webp", "ans": 3, "page": 300, "q": 122, "diff": 2, "src": "82. 83. 91. 98. 산업기사"}, {"id": "machine_0506", "img": "q/machine/0506.webp", "ans": 3, "page": 300, "q": 123, "diff": 0, "src": ""}, {"id": "machine_0507", "img": "q/machine/0507.webp", "ans": 3, "page": 300, "q": 124, "diff": 0, "src": ""}, {"id": "machine_0508", "img": "q/machine/0508.webp", "ans": 3, "page": 301, "q": 126, "diff": 0, "src": ""}, {"id": "machine_0509", "img": "q/machine/0509.webp", "ans": 1, "page": 302, "q": 129, "diff": 5, "src": "92. 94. 98. 00. 기사, 79. 83. 산업기사, ® : 67. 산업기사"}, {"id": "machine_0510", "img": "q/machine/0510.webp", "ans": 4, "page": 302, "q": 131, "diff": 0, "src": ""}, {"id": "machine_0511", "img": "q/machine/0511.webp", "ans": 1, "page": 302, "q": 132, "diff": 0, "src": ""}, {"id": "machine_0512", "img": "q/machine/0512.webp", "ans": 2, "page": 303, "q": 133, "diff": 1, "src": "70. 기사"}, {"id": "machine_0513", "img": "q/machine/0513.webp", "ans": 4, "page": 303, "q": 134, "diff": 1, "src": ""}, {"id": "machine_0514", "img": "q/machine/0514.webp", "ans": 1, "page": 303, "q": 135, "diff": 0, "src": ""}, {"id": "machine_0515", "img": "q/machine/0515.webp", "ans": 1, "page": 303, "q": 136, "diff": 1, "src": "92.10. 기사, 16.18. 산업기사"}, {"id": "machine_0516", "img": "q/machine/0516.webp", "ans": 1, "page": 303, "q": 137, "diff": 4, "src": ""}, {"id": "machine_0517", "img": "q/machine/0517.webp", "ans": 4, "page": 304, "q": 138, "diff": 2, "src": "85. 기사, 84. 산업기사, ® : 84. 산업기사"}, {"id": "machine_0518", "img": "q/machine/0518.webp", "ans": 1, "page": 305, "q": 140, "diff": 0, "src": ""}, {"id": "machine_0519", "img": "q/machine/0519.webp", "ans": 2, "page": 305, "q": 141, "diff": 0, "src": ""}, {"id": "machine_0520", "img": "q/machine/0520.webp", "ans": 2, "page": 305, "q": 142, "diff": 3, "src": "95. 99.11. 기사, 75. 97.12. 산업기사"}, {"id": "machine_0521", "img": "q/machine/0521.webp", "ans": 3, "page": 305, "q": 143, "diff": 0, "src": ""}, {"id": "machine_0522", "img": "q/machine/0522.webp", "ans": 3, "page": 306, "q": 144, "diff": 3, "src": "90. 95.11. 기사, 83. 91. 00. 05. 산업기사"}, {"id": "machine_0523", "img": "q/machine/0523.webp", "ans": 3, "page": 306, "q": 145, "diff": 1, "src": "83.98.00. 기사"}, {"id": "machine_0524", "img": "q/machine/0524.webp", "ans": 3, "page": 306, "q": 147, "diff": 1, "src": "83.99. （）1.산업기사"}, {"id": "machine_0525", "img": "q/machine/0525.webp", "ans": 4, "page": 307, "q": 148, "diff": 2, "src": "87.95. 기사"}, {"id": "machine_0526", "img": "q/machine/0526.webp", "ans": 4, "page": 307, "q": 149, "diff": 2, "src": "95.97.기사"}, {"id": "machine_0527", "img": "q/machine/0527.webp", "ans": 2, "page": 307, "q": 150, "diff": 1, "src": "85. 93. 99. 산업기사"}, {"id": "machine_0528", "img": "q/machine/0528.webp", "ans": 1, "page": 307, "q": 151, "diff": 2, "src": "（）3. 기사, 93. 98. 00. 01. 산업기사"}, {"id": "machine_0529", "img": "q/machine/0529.webp", "ans": 3, "page": 308, "q": 153, "diff": 5, "src": "76. 90. 96. 98. 00. 03. 기사"}, {"id": "machine_0530", "img": "q/machine/0530.webp", "ans": 2, "page": 308, "q": 154, "diff": 5, "src": "82. 83. 87. 95. 03. 기사, 81. 84. 90. 98. 산업기사"}, {"id": "machine_0531", "img": "q/machine/0531.webp", "ans": 3, "page": 308, "q": 155, "diff": 1, "src": "84. 88. 00. 산업기사"}, {"id": "machine_0532", "img": "q/machine/0532.webp", "ans": 1, "page": 308, "q": 156, "diff": 5, "src": "93. 96. 99. 01. 기사, 84. 89. 90. 94. 97. 98. 산업기사"}, {"id": "machine_0533", "img": "q/machine/0533.webp", "ans": 1, "page": 308, "q": 157, "diff": 0, "src": ""}, {"id": "machine_0534", "img": "q/machine/0534.webp", "ans": 4, "page": 309, "q": 158, "diff": 0, "src": ""}, {"id": "machine_0535", "img": "q/machine/0535.webp", "ans": 3, "page": 309, "q": 159, "diff": 0, "src": ""}, {"id": "machine_0536", "img": "q/machine/0536.webp", "ans": 3, "page": 310, "q": 163, "diff": 1, "src": ""}, {"id": "machine_0537", "img": "q/machine/0537.webp", "ans": 2, "page": 310, "q": 164, "diff": 2, "src": "85.87. 92.95. 산업기사"}, {"id": "machine_0538", "img": "q/machine/0538.webp", "ans": 4, "page": 311, "q": 165, "diff": 1, "src": "98.99.기사"}, {"id": "machine_0539", "img": "q/machine/0539.webp", "ans": 4, "page": 311, "q": 166, "diff": 2, "src": "76.95. 기사"}, {"id": "machine_0540", "img": "q/machine/0540.webp", "ans": 4, "page": 312, "q": 167, "diff": 0, "src": "77. 89. 01. 산업기사"}, {"id": "machine_0541", "img": "q/machine/0541.webp", "ans": 2, "page": 312, "q": 168, "diff": 1, "src": "83. 기사, 98. 산업기사"}, {"id": "machine_0542", "img": "q/machine/0542.webp", "ans": 4, "page": 314, "q": 172, "diff": 4, "src": "89. 93. 기사, 81. 82. 90. 92. 98. 산업기사"}, {"id": "machine_0543", "img": "q/machine/0543.webp", "ans": 1, "page": 314, "q": 173, "diff": 1, "src": "98.01.05.산업기사"}, {"id": "machine_0544", "img": "q/machine/0544.webp", "ans": 1, "page": 314, "q": 174, "diff": 2, "src": "82. 83. 기사"}, {"id": "machine_0545", "img": "q/machine/0545.webp", "ans": 2, "page": 314, "q": 175, "diff": 1, "src": ""}, {"id": "machine_0546", "img": "q/machine/0546.webp", "ans": 4, "page": 315, "q": 178, "diff": 1, "src": "89. 91. 98. 산업기사"}, {"id": "machine_0547", "img": "q/machine/0547.webp", "ans": 3, "page": 316, "q": 181, "diff": 5, "src": ""}, {"id": "machine_0548", "img": "q/machine/0548.webp", "ans": 3, "page": 320, "q": 1, "diff": 0, "src": ""}, {"id": "machine_0549", "img": "q/machine/0549.webp", "ans": 2, "page": 320, "q": 2, "diff": 1, "src": ""}, {"id": "machine_0550", "img": "q/machine/0550.webp", "ans": 2, "page": 320, "q": 3, "diff": 1, "src": "92. 기사"}, {"id": "machine_0551", "img": "q/machine/0551.webp", "ans": 1, "page": 321, "q": 4, "diff": 5, "src": ""}, {"id": "machine_0552", "img": "q/machine/0552.webp", "ans": 1, "page": 321, "q": 5, "diff": 0, "src": "93. 산업기사"}, {"id": "machine_0553", "img": "q/machine/0553.webp", "ans": 4, "page": 321, "q": 6, "diff": 1, "src": "84.91.12.18.산업기사"}, {"id": "machine_0554", "img": "q/machine/0554.webp", "ans": 3, "page": 322, "q": 7, "diff": 3, "src": "93. 99. 기사, 84. 91. 00. 산업기사"}, {"id": "machine_0555", "img": "q/machine/0555.webp", "ans": 4, "page": 322, "q": 8, "diff": 1, "src": "99. 00. 산업기사"}, {"id": "machine_0556", "img": "q/machine/0556.webp", "ans": 4, "page": 322, "q": 9, "diff": 1, "src": "83. 97. 00. 산업기사, 05 기사"}, {"id": "machine_0557", "img": "q/machine/0557.webp", "ans": 2, "page": 322, "q": 10, "diff": 0, "src": ""}, {"id": "machine_0558", "img": "q/machine/0558.webp", "ans": 2, "page": 323, "q": 11, "diff": 3, "src": ""}, {"id": "machine_0559", "img": "q/machine/0559.webp", "ans": 4, "page": 323, "q": 12, "diff": 1, "src": "90. 기사, 79. 81. 82. 83. 99. 01. 산업기사"}, {"id": "machine_0560", "img": "q/machine/0560.webp", "ans": 4, "page": 323, "q": 13, "diff": 1, "src": "82. 기사 ® :05. 산업기사"}, {"id": "machine_0561", "img": "q/machine/0561.webp", "ans": 2, "page": 323, "q": 14, "diff": 1, "src": "01.09. 기사, ® ： 11. 산업기사"}, {"id": "machine_0562", "img": "q/machine/0562.webp", "ans": 4, "page": 323, "q": 15, "diff": 1, "src": ""}, {"id": "machine_0563", "img": "q/machine/0563.webp", "ans": 2, "page": 324, "q": 16, "diff": 0, "src": "11. 기사, 95. 05. 산업기사"}, {"id": "machine_0564", "img": "q/machine/0564.webp", "ans": 1, "page": 324, "q": 17, "diff": 4, "src": "82. 83. 90. 기사, 98. 00. 산업기사"}, {"id": "machine_0565", "img": "q/machine/0565.webp", "ans": 3, "page": 325, "q": 18, "diff": 0, "src": "97.산업기사"}, {"id": "machine_0566", "img": "q/machine/0566.webp", "ans": 1, "page": 325, "q": 19, "diff": 0, "src": ""}, {"id": "machine_0567", "img": "q/machine/0567.webp", "ans": 4, "page": 325, "q": 20, "diff": 0, "src": ""}, {"id": "machine_0568", "img": "q/machine/0568.webp", "ans": 1, "page": 325, "q": 21, "diff": 0, "src": ""}, {"id": "machine_0569", "img": "q/machine/0569.webp", "ans": 4, "page": 326, "q": 22, "diff": 5, "src": ""}, {"id": "machine_0570", "img": "q/machine/0570.webp", "ans": 4, "page": 326, "q": 23, "diff": 1, "src": "01. 기사"}, {"id": "machine_0571", "img": "q/machine/0571.webp", "ans": 2, "page": 326, "q": 24, "diff": 1, "src": "02.11.기사"}, {"id": "machine_0572", "img": "q/machine/0572.webp", "ans": 2, "page": 326, "q": 25, "diff": 4, "src": "86. 91.98.00. 04.20. 기사"}, {"id": "machine_0573", "img": "q/machine/0573.webp", "ans": 4, "page": 339, "q": 1, "diff": 0, "src": ""}, {"id": "machine_0574", "img": "q/machine/0574.webp", "ans": 4, "page": 339, "q": 2, "diff": 0, "src": ""}, {"id": "machine_0575", "img": "q/machine/0575.webp", "ans": 3, "page": 339, "q": 3, "diff": 0, "src": ""}, {"id": "machine_0576", "img": "q/machine/0576.webp", "ans": 3, "page": 340, "q": 6, "diff": 1, "src": "85. 97. 산업기사, 節 : 78. 82. 83. 산업기사"}, {"id": "machine_0577", "img": "q/machine/0577.webp", "ans": 2, "page": 342, "q": 8, "diff": 0, "src": ""}, {"id": "machine_0578", "img": "q/machine/0578.webp", "ans": 1, "page": 342, "q": 9, "diff": 0, "src": ""}, {"id": "machine_0579", "img": "q/machine/0579.webp", "ans": 3, "page": 342, "q": 10, "diff": 1, "src": "85.92. 산업기사"}, {"id": "machine_0580", "img": "q/machine/0580.webp", "ans": 2, "page": 342, "q": 11, "diff": 0, "src": ""}, {"id": "machine_0581", "img": "q/machine/0581.webp", "ans": 4, "page": 343, "q": 12, "diff": 3, "src": "97. 기사, 80. 82. 83. 89. 산업기사"}, {"id": "machine_0582", "img": "q/machine/0582.webp", "ans": 2, "page": 343, "q": 13, "diff": 1, "src": ""}, {"id": "machine_0583", "img": "q/machine/0583.webp", "ans": 2, "page": 343, "q": 16, "diff": 2, "src": "93.97.기사"}, {"id": "machine_0584", "img": "q/machine/0584.webp", "ans": 2, "page": 344, "q": 17, "diff": 0, "src": ""}, {"id": "machine_0585", "img": "q/machine/0585.webp", "ans": 4, "page": 344, "q": 18, "diff": 0, "src": ""}, {"id": "machine_0586", "img": "q/machine/0586.webp", "ans": 4, "page": 345, "q": 19, "diff": 0, "src": ""}, {"id": "machine_0587", "img": "q/machine/0587.webp", "ans": 3, "page": 345, "q": 20, "diff": 0, "src": ""}, {"id": "machine_0588", "img": "q/machine/0588.webp", "ans": 4, "page": 345, "q": 21, "diff": 0, "src": ""}, {"id": "machine_0589", "img": "q/machine/0589.webp", "ans": 1, "page": 345, "q": 22, "diff": 0, "src": ""}, {"id": "machine_0590", "img": "q/machine/0590.webp", "ans": 1, "page": 345, "q": 23, "diff": 1, "src": ""}, {"id": "machine_0591", "img": "q/machine/0591.webp", "ans": 4, "page": 346, "q": 24, "diff": 0, "src": ""}, {"id": "machine_0592", "img": "q/machine/0592.webp", "ans": 2, "page": 346, "q": 25, "diff": 0, "src": "89. 99. 01. 기사, 84. 91. 산업기사"}, {"id": "machine_0593", "img": "q/machine/0593.webp", "ans": 1, "page": 346, "q": 26, "diff": 1, "src": "91.00.기사"}, {"id": "machine_0594", "img": "q/machine/0594.webp", "ans": 3, "page": 346, "q": 27, "diff": 1, "src": ""}, {"id": "machine_0595", "img": "q/machine/0595.webp", "ans": 4, "page": 347, "q": 28, "diff": 0, "src": ""}, {"id": "machine_0596", "img": "q/machine/0596.webp", "ans": 4, "page": 347, "q": 29, "diff": 0, "src": ""}, {"id": "machine_0597", "img": "q/machine/0597.webp", "ans": 2, "page": 347, "q": 30, "diff": 0, "src": ""}, {"id": "machine_0598", "img": "q/machine/0598.webp", "ans": 1, "page": 347, "q": 31, "diff": 1, "src": "83. 기사, 82. 83.97. 산업기사"}, {"id": "machine_0599", "img": "q/machine/0599.webp", "ans": 1, "page": 347, "q": 32, "diff": 3, "src": ""}, {"id": "machine_0600", "img": "q/machine/0600.webp", "ans": 1, "page": 347, "q": 33, "diff": 0, "src": ""}, {"id": "machine_0601", "img": "q/machine/0601.webp", "ans": 4, "page": 348, "q": 34, "diff": 0, "src": ""}, {"id": "machine_0602", "img": "q/machine/0602.webp", "ans": 2, "page": 348, "q": 35, "diff": 0, "src": "94. 98.05. 기사, 05 산업기사"}, {"id": "machine_0603", "img": "q/machine/0603.webp", "ans": 2, "page": 348, "q": 36, "diff": 0, "src": ""}, {"id": "machine_0604", "img": "q/machine/0604.webp", "ans": 3, "page": 348, "q": 37, "diff": 2, "src": "92. 97. 03.10. 기사"}, {"id": "machine_0605", "img": "q/machine/0605.webp", "ans": 3, "page": 349, "q": 38, "diff": 0, "src": ""}, {"id": "machine_0606", "img": "q/machine/0606.webp", "ans": 2, "page": 349, "q": 39, "diff": 0, "src": ""}, {"id": "machine_0607", "img": "q/machine/0607.webp", "ans": 4, "page": 350, "q": 41, "diff": 0, "src": ""}, {"id": "machine_0608", "img": "q/machine/0608.webp", "ans": 4, "page": 351, "q": 43, "diff": 1, "src": "98. 기사"}, {"id": "machine_0609", "img": "q/machine/0609.webp", "ans": 1, "page": 352, "q": 44, "diff": 0, "src": ""}, {"id": "machine_0610", "img": "q/machine/0610.webp", "ans": 2, "page": 352, "q": 45, "diff": 0, "src": ""}, {"id": "machine_0611", "img": "q/machine/0611.webp", "ans": 1, "page": 352, "q": 46, "diff": 0, "src": ""}, {"id": "machine_0612", "img": "q/machine/0612.webp", "ans": 2, "page": 353, "q": 47, "diff": 0, "src": ""}, {"id": "machine_0613", "img": "q/machine/0613.webp", "ans": 4, "page": 353, "q": 48, "diff": 0, "src": ""}, {"id": "machine_0614", "img": "q/machine/0614.webp", "ans": 2, "page": 353, "q": 49, "diff": 2, "src": ""}, {"id": "machine_0615", "img": "q/machine/0615.webp", "ans": 1, "page": 354, "q": 51, "diff": 0, "src": ""}, {"id": "machine_0616", "img": "q/machine/0616.webp", "ans": 2, "page": 355, "q": 53, "diff": 0, "src": ""}, {"id": "machine_0617", "img": "q/machine/0617.webp", "ans": 3, "page": 355, "q": 54, "diff": 0, "src": ""}, {"id": "machine_0618", "img": "q/machine/0618.webp", "ans": 4, "page": 356, "q": 55, "diff": 0, "src": ""}, {"id": "machine_0619", "img": "q/machine/0619.webp", "ans": 2, "page": 356, "q": 56, "diff": 0, "src": ""}, {"id": "machine_0620", "img": "q/machine/0620.webp", "ans": 1, "page": 356, "q": 57, "diff": 3, "src": ""}, {"id": "machine_0621", "img": "q/machine/0621.webp", "ans": 2, "page": 357, "q": 58, "diff": 5, "src": "83. 88. 96. 97. 99. 04. 06. 08. 기사, 82. 83. 86.11. 산업기사"}, {"id": "machine_0622", "img": "q/machine/0622.webp", "ans": 1, "page": 357, "q": 59, "diff": 0, "src": ""}, {"id": "machine_0623", "img": "q/machine/0623.webp", "ans": 4, "page": 357, "q": 60, "diff": 0, "src": ""}, {"id": "machine_0624", "img": "q/machine/0624.webp", "ans": 2, "page": 357, "q": 61, "diff": 0, "src": ""}, {"id": "machine_0625", "img": "q/machine/0625.webp", "ans": 4, "page": 358, "q": 62, "diff": 1, "src": "86. 기사"}, {"id": "machine_0626", "img": "q/machine/0626.webp", "ans": 3, "page": 358, "q": 63, "diff": 0, "src": ""}, {"id": "machine_0627", "img": "q/machine/0627.webp", "ans": 1, "page": 358, "q": 64, "diff": 3, "src": "86. 88. 98. 05. 기사"}, {"id": "machine_0628", "img": "q/machine/0628.webp", "ans": 2, "page": 359, "q": 65, "diff": 0, "src": ""}, {"id": "machine_0629", "img": "q/machine/0629.webp", "ans": 3, "page": 359, "q": 66, "diff": 1, "src": "92. 05. 기사"}, {"id": "machine_0630", "img": "q/machine/0630.webp", "ans": 3, "page": 359, "q": 67, "diff": 1, "src": "88. 기사"}, {"id": "machine_0631", "img": "q/machine/0631.webp", "ans": 1, "page": 360, "q": 69, "diff": 0, "src": ""}, {"id": "machine_0632", "img": "q/machine/0632.webp", "ans": 2, "page": 360, "q": 70, "diff": 2, "src": "83.85. 89. 98. 00. 기사, 83. 88. 97. 99. 산업기사"}, {"id": "machine_0633", "img": "q/machine/0633.webp", "ans": 3, "page": 363, "q": 73, "diff": 0, "src": ""}, {"id": "machine_0634", "img": "q/machine/0634.webp", "ans": 3, "page": 363, "q": 74, "diff": 0, "src": ""}, {"id": "machine_0635", "img": "q/machine/0635.webp", "ans": 2, "page": 363, "q": 75, "diff": 0, "src": ""}, {"id": "machine_0636", "img": "q/machine/0636.webp", "ans": 2, "page": 364, "q": 76, "diff": 0, "src": ""}, {"id": "machine_0637", "img": "q/machine/0637.webp", "ans": 1, "page": 364, "q": 77, "diff": 0, "src": ""}, {"id": "machine_0638", "img": "q/machine/0638.webp", "ans": 3, "page": 364, "q": 78, "diff": 0, "src": ""}, {"id": "machine_0639", "img": "q/machine/0639.webp", "ans": 1, "page": 365, "q": 79, "diff": 0, "src": ""}, {"id": "machine_0640", "img": "q/machine/0640.webp", "ans": 3, "page": 366, "q": 80, "diff": 0, "src": ""}, {"id": "machine_0641", "img": "q/machine/0641.webp", "ans": 2, "page": 367, "q": 82, "diff": 0, "src": ""}, {"id": "machine_0642", "img": "q/machine/0642.webp", "ans": 2, "page": 368, "q": 83, "diff": 0, "src": ""}, {"id": "machine_0643", "img": "q/machine/0643.webp", "ans": 4, "page": 368, "q": 84, "diff": 0, "src": ""}, {"id": "machine_0644", "img": "q/machine/0644.webp", "ans": 3, "page": 368, "q": 85, "diff": 0, "src": ""}, {"id": "machine_0645", "img": "q/machine/0645.webp", "ans": 3, "page": 368, "q": 86, "diff": 0, "src": ""}, {"id": "machine_0646", "img": "q/machine/0646.webp", "ans": 2, "page": 369, "q": 87, "diff": 0, "src": ""}, {"id": "machine_0647", "img": "q/machine/0647.webp", "ans": 3, "page": 369, "q": 88, "diff": 1, "src": "01.11.기사"}, {"id": "machine_0648", "img": "q/machine/0648.webp", "ans": 4, "page": 369, "q": 89, "diff": 1, "src": "92. 기사"}, {"id": "machine_0649", "img": "q/machine/0649.webp", "ans": 1, "page": 370, "q": 90, "diff": 1, "src": ""}, {"id": "machine_0650", "img": "q/machine/0650.webp", "ans": 4, "page": 370, "q": 91, "diff": 0, "src": ""}, {"id": "machine_0651", "img": "q/machine/0651.webp", "ans": 3, "page": 370, "q": 92, "diff": 0, "src": ""}, {"id": "machine_0652", "img": "q/machine/0652.webp", "ans": 2, "page": 371, "q": 93, "diff": 0, "src": "96.산업기사"}, {"id": "machine_0653", "img": "q/machine/0653.webp", "ans": 4, "page": 371, "q": 94, "diff": 1, "src": "00.01. 산업기사"}, {"id": "machine_0654", "img": "q/machine/0654.webp", "ans": 3, "page": 371, "q": 95, "diff": 1, "src": ""}, {"id": "machine_0655", "img": "q/machine/0655.webp", "ans": 4, "page": 371, "q": 96, "diff": 0, "src": ""}]